[{"source": "suumo", "property_type": "shinchiku", "url": "https://suumo.jp/ms/shinchiku/tokyo/sc_minato/nc_67732748/", "name": "リビオ三田レジデンス", "price_man": null, "price_max_man": null, "address": "港区芝５", "station_line": "都営三田線/三田 徒歩5分", "walk_min": 5, "area_m2": 118.0, "area_max_m2": 118.0, "layout": "1LDK～3LDK", "delivery_date": "2027年8月下旬予定", "total_units": 50, "floor_total": 14, "list_ward_roman": "minato", "built_str": "", "built_year": null, "floor_position": null, "floor_structure": null, "ownership": null, "duplicate_count": 1, "ss_sumai_surfin_url": "https://www.sumai-surfin.com/re/49646/", "ss_profit_pct": 53, "ss_address": "東京都港区芝５－２－９３", "ss_favorite_count": 51, "ss_lookup_status": "found", "ss_sim_base_price": 6000, "ss_purchase_judgment": "条件付きで値上がりが期待できます", "commute_info": "{\"playground\": {\"minutes\": 18, \"summary\": \"Google Maps経路 (朝9:00到着)\", \"calculatedAt\": \"2026-03-25T06:29:41Z\", \"source\": \"gmaps\"}, \"m3career\": {\"minutes\": 9, \"summary\": \"Google Maps経路 (朝9:00到着)\", \"calculatedAt\": \"2026-03-25T06:29:41Z\", \"source\": \"gmaps\"}}", "is_new": false, "is_new_building": false, "price_history": [], "first_seen_at": "2026-02-25", "competing_listings_count": 1, "price_fairness_score": null, "resale_liquidity_score": 74, "listing_score": 72}, {"source": "suumo", "property_type": "shinchiku", "url": "https://suumo.jp/ms/shinchiku/tokyo/sc_adachi/nc_67732826/", "name": "バウス北綾瀬タワー", "price_man": 8448, "price_max_man": 12798, "address": "足立区谷中２", "station_line": "東京メトロ千代田線/北綾瀬 徒歩3分", "walk_min": 3, "area_m2": 70.0, "area_max_m2": 70.0, "layout": "3LDK", "delivery_date": "2028年4月上旬予定", "total_units": null, "floor_total": null, "list_ward_roman": "adachi", "built_str": "", "built_year": null, "floor_position": null, "floor_structure": null, "ownership": null, "duplicate_count": 1, "latitude": 35.7785388, "longitude": 139.8333733, "ss_sumai_surfin_url": "https://www.sumai-surfin.com/re/49576/", "ss_profit_pct": 29, "ss_address": "東京都足立区谷中２－１－１", "ss_favorite_count": 47, "ss_lookup_status": "found", "ss_sim_base_price": 6000, "ss_purchase_judgment": "条件付きで値上がりが期待できます", "geocode_confidence": "high", "hazard_info": "{\"flood\": true, \"sediment\": false, \"storm_surge\": true, \"tsunami\": false, \"liquefaction\": false, \"inland_water\": false, \"building_collapse\": 2, \"fire\": 1, \"combined\": 2}", "commute_info": "{\"playground\": {\"minutes\": 40, \"summary\": \"Google Maps経路 (朝9:00到着)\", \"calculatedAt\": \"2026-03-25T06:29:41Z\", \"source\": \"gmaps\"}, \"m3career\": {\"minutes\": 50, \"summary\": \"Google Maps経路 (朝9:00到着)\", \"calculatedAt\": \"2026-03-25T06:29:41Z\", \"source\": \"gmaps\"}}", "is_new": false, "is_new_building": false, "price_history": [{"date": "2026-03-27", "price_man": 8448}], "first_seen_at": "2026-02-25", "competing_listings_count": 1, "price_fairness_score": null, "resale_liquidity_score": 69, "listing_score": 43}, {"source": "suumo", "property_type": "shinchiku", "url": "https://suumo.jp/ms/shinchiku/tokyo/sc_minato/nc_67735783/", "name": "グランスイート麻布六本木", "price_man": null, "price_max_man": null, "address": "港区六本木３", "station_line": "東京メトロ南北線/六本木一丁目 徒歩4分", "walk_min": 4, "area_m2": null, "area_max_m2": null, "layout": "1K～2LDK", "delivery_date": "2026年7月予定", "total_units": null, "floor_total": null, "list_ward_roman": "minato", "built_str": "", "built_year": null, "floor_position": null, "floor_structure": null, "ownership": null, "duplicate_count": 1, "ss_sumai_surfin_url": "https://www.sumai-surfin.com/re/49684/", "ss_address": "東京都港区六本木３－１６－８", "ss_favorite_count": 50, "ss_lookup_status": "found", "ss_sim_base_price": 6000, "ss_purchase_judgment": "条件付きで値上がりが期待できます", "commute_info": "{\"playground\": {\"minutes\": 12, \"summary\": \"Google Maps経路 (朝9:00到着)\", \"calculatedAt\": \"2026-03-25T06:29:41Z\", \"source\": \"gmaps\"}, \"m3career\": {\"minutes\": 5, \"summary\": \"Google Maps経路 (朝9:00到着)\", \"calculatedAt\": \"2026-03-25T06:29:41Z\", \"source\": \"gmaps\"}}", "is_new": false, "is_new_building": false, "price_history": [], "first_seen_at": "2026-02-25", "competing_listings_count": 1, "price_fairness_score": null, "resale_liquidity_score": 82, "listing_score": 86}, {"source": "suumo", "property_type": "shinchiku", "url": "https://suumo.jp/ms/shinchiku/tokyo/sc_minato/nc_67726518/", "name": "リビオタワー品川", "price_man": null, "price_max_man": null, "address": "港区港南３", "station_line": "ＪＲ山手線/品川 徒歩13分", "walk_min": 13, "area_m2": null, "area_max_m2": null, "layout": "1LDK～3LDK", "delivery_date": "2027年4月上旬予定", "total_units": null, "floor_total": null, "list_ward_roman": "minato", "built_str": "", "built_year": null, "floor_position": null, "floor_structure": null, "ownership": null, "duplicate_count": 1, "ss_sumai_surfin_url": "https://www.sumai-surfin.com/re/48034/", "ss_profit_pct": 87, "ss_address": "東京都港区港南３－７－２", "ss_favorite_count": 155, "ss_lookup_status": "found", "ss_sim_base_price": 6000, "ss_purchase_judgment": "条件付きで値上がりが期待できます", "commute_info": "{\"playground\": {\"minutes\": 20, \"summary\": \"Google Maps経路 (朝9:00到着)\", \"calculatedAt\": \"2026-03-25T06:29:41Z\", \"source\": \"gmaps\"}, \"m3career\": {\"minutes\": 18, \"summary\": \"Google Maps経路 (朝9:00到着)\", \"calculatedAt\": \"2026-03-25T06:29:41Z\", \"source\": \"gmaps\"}}", "is_new": false, "is_new_building": false, "price_history": [], "first_seen_at": "2026-03-15", "competing_listings_count": 1, "price_fairness_score": null, "resale_liquidity_score": 67, "listing_score": 81}, {"source": "suumo", "property_type": "shinchiku", "url": "https://suumo.jp/ms/shinchiku/tokyo/sc_bunkyo/nc_67729040/", "name": "リビオシティ文京小石川", "price_man": 11690, "price_max_man": 15490, "address": "文京区小石川４", "station_line": "東京メトロ丸ノ内線/後楽園 徒歩12分", "walk_min": 12, "area_m2": 2000.0, "area_max_m2": 2000.0, "layout": "2LDK～3LDK", "delivery_date": "2027年2月下旬予定", "total_units": 522, "floor_total": null, "list_ward_roman": "bunkyo", "built_str": "", "built_year": null, "floor_position": null, "floor_structure": null, "ownership": "金含む", "duplicate_count": 1, "ss_sumai_surfin_url": "https://www.sumai-surfin.com/re/48033/", "ss_profit_pct": 92, "ss_address": "東京都文京区小石川４－７０－１７", "ss_favorite_count": 169, "ss_lookup_status": "found", "ss_sim_base_price": 6000, "ss_purchase_judgment": "条件付きで値上がりが期待できます", "commute_info": "{\"playground\": {\"minutes\": 18, \"summary\": \"Google Maps経路 (朝9:00到着)\", \"calculatedAt\": \"2026-03-25T06:29:41Z\", \"source\": \"gmaps\"}, \"m3career\": {\"minutes\": 24, \"summary\": \"Google Maps経路 (朝9:00到着)\", \"calculatedAt\": \"2026-03-25T06:29:41Z\", \"source\": \"gmaps\"}}", "is_new": false, "is_new_building": false, "price_history": [{"date": "2026-03-25", "price_man": 11690}], "first_seen_at": "2026-03-15", "competing_listings_count": 1, "price_fairness_score": null, "resale_liquidity_score": 70, "listing_score": 79}, {"source": "suumo", "property_type": "shinchiku", "url": "https://suumo.jp/ms/shinchiku/tokyo/sc_minato/nc_67734044/", "name": "アトラス三田", "price_man": null, "price_max_man": null, "address": "港区三田２", "station_line": "都営三田線/三田 徒歩8分", "walk_min": 8, "area_m2": null, "area_max_m2": null, "layout": "2LDK", "delivery_date": "2027年8月下旬予定", "total_units": 69, "floor_total": 13, "list_ward_roman": "minato", "built_str": "", "built_year": null, "floor_position": null, "floor_structure": null, "ownership": null, "duplicate_count": 1, "ss_sumai_surfin_url": "https://www.sumai-surfin.com/re/49618/", "ss_profit_pct": 86, "ss_address": "東京都港区三田２－８－３", "ss_favorite_count": 54, "ss_lookup_status": "found", "ss_sim_base_price": 6000, "ss_purchase_judgment": "条件付きで値上がりが期待できます", "commute_info": "{\"playground\": {\"minutes\": 16, \"summary\": \"Google Maps経路 (朝9:00到着)\", \"calculatedAt\": \"2026-03-25T06:29:41Z\", \"source\": \"gmaps\"}, \"m3career\": {\"minutes\": 7, \"summary\": \"Google Maps経路 (朝9:00到着)\", \"calculatedAt\": \"2026-03-25T06:29:41Z\", \"source\": \"gmaps\"}}", "is_new": false, "is_new_building": false, "price_history": [], "first_seen_at": "2026-03-25", "competing_listings_count": 1, "price_fairness_score": null, "resale_liquidity_score": 66, "listing_score": 80}, {"source": "suumo", "property_type": "shinchiku", "url": "https://suumo.jp/ms/shinchiku/tokyo/sc_itabashi/nc_67728816/", "name": "バウス加賀", "price_man": null, "price_max_man": null, "address": "板橋区加賀１", "station_line": "都営三田線/新板橋 徒歩10分", "walk_min": 10, "area_m2": 73.0, "area_max_m2": 110.0, "layout": "3LDK", "delivery_date": "2026年9月中旬予定", "total_units": 228, "floor_total": null, "list_ward_roman": "itabashi", "built_str": "", "built_year": null, "floor_position": null, "floor_structure": null, "ownership": null, "duplicate_count": 1, "latitude": 35.7567663, "longitude": 139.7162427, "ss_sumai_surfin_url": "https://www.sumai-surfin.com/re/49107/", "ss_profit_pct": 61, "ss_address": "東京都板橋区加賀１－３３５６－１", "ss_favorite_count": 51, "ss_lookup_status": "found", "ss_sim_base_price": 6000, "ss_purchase_judgment": "条件付きで値上がりが期待できます", "geocode_confidence": "high", "hazard_info": "{\"flood\": true, \"sediment\": false, \"storm_surge\": false, \"tsunami\": false, \"liquefaction\": false, \"inland_water\": false, \"building_collapse\": 1, \"fire\": 1, \"combined\": 1}", "commute_info": "{\"playground\": {\"minutes\": 26, \"summary\": \"Google Maps経路 (朝9:00到着)\", \"calculatedAt\": \"2026-03-25T06:29:41Z\", \"source\": \"gmaps\"}, \"m3career\": {\"minutes\": 30, \"summary\": \"Google Maps経路 (朝9:00到着)\", \"calculatedAt\": \"2026-03-25T06:29:41Z\", \"source\": \"gmaps\"}}", "is_new": false, "is_new_building": false, "price_history": [], "first_seen_at": "2026-03-15", "competing_listings_count": 1, "price_fairness_score": null, "resale_liquidity_score": 61, "listing_score": 59}, {"source": "suumo", "property_type": "shinchiku", "url": "https://suumo.jp/ms/shinchiku/tokyo/sc_bunkyo/nc_67733992/", "name": "アトラス文京安藤坂", "price_man": null, "price_max_man": null, "address": "文京区春日２", "station_line": "東京メトロ丸ノ内線/後楽園 徒歩9分", "walk_min": 9, "area_m2": null, "area_max_m2": null, "layout": "3LDK", "delivery_date": "2027年4月下旬予定", "total_units": 70, "floor_total": null, "list_ward_roman": "bunkyo", "built_str": "", "built_year": null, "floor_position": null, "floor_structure": null, "ownership": null, "duplicate_count": 1, "ss_sumai_surfin_url": "https://www.sumai-surfin.com/re/48968/", "ss_profit_pct": 78, "ss_address": "東京都文京区春日２－１０７－３２", "ss_favorite_count": 92, "ss_lookup_status": "found", "ss_sim_base_price": 6000, "ss_purchase_judgment": "条件付きで値上がりが期待できます", "commute_info": "{\"playground\": {\"minutes\": 14, \"summary\": \"Google Maps経路 (朝9:00到着)\", \"calculatedAt\": \"2026-03-25T06:29:41Z\", \"source\": \"gmaps\"}, \"m3career\": {\"minutes\": 20, \"summary\": \"Google Maps経路 (朝9:00到着)\", \"calculatedAt\": \"2026-03-25T06:29:41Z\", \"source\": \"gmaps\"}}", "is_new": false, "is_new_building": false, "price_history": [], "first_seen_at": "2026-03-15", "competing_listings_count": 1, "price_fairness_score": null, "resale_liquidity_score": 66, "listing_score": 78}, {"source": "suumo", "property_type": "shinchiku", "url": "https://suumo.jp/ms/shinchiku/tokyo/sc_chuo/nc_67728904/", "name": "THE TOYOMI TOWER MARINE&SKY", "price_man": null, "price_max_man": null, "address": "中央区豊海町", "station_line": "都営大江戸線/勝どき 徒歩10分", "walk_min": 10, "area_m2": null, "area_max_m2": null, "layout": "1LDK～3LDK", "delivery_date": "2027年8月下旬予定", "total_units": null, "floor_total": 53, "list_ward_roman": "chuo", "built_str": "", "built_year": null, "floor_position": null, "floor_structure": null, "ownership": null, "duplicate_count": 1, "latitude": 35.6533124, "longitude": 139.7693873, "ss_sumai_surfin_url": "https://www.sumai-surfin.com/re/47668/", "ss_profit_pct": 88, "ss_address": "東京都中央区豊海町４１", "ss_favorite_count": 102, "ss_lookup_status": "found", "ss_sim_base_price": 6000, "ss_purchase_judgment": "条件付きで値上がりが期待できます", "geocode_confidence": "high", "hazard_info": "{\"flood\": true, \"sediment\": false, \"storm_surge\": true, \"tsunami\": false, \"liquefaction\": false, \"inland_water\": false, \"building_collapse\": 1, \"fire\": 1, \"combined\": 1}", "commute_info": "{\"playground\": {\"minutes\": 18, \"summary\": \"Google Maps経路 (朝9:00到着)\", \"calculatedAt\": \"2026-03-25T06:29:41Z\", \"source\": \"gmaps\"}, \"m3career\": {\"minutes\": 12, \"summary\": \"Google Maps経路 (朝9:00到着)\", \"calculatedAt\": \"2026-03-25T06:29:41Z\", \"source\": \"gmaps\"}}", "is_new": false, "is_new_building": false, "price_history": [], "first_seen_at": "2026-03-15", "competing_listings_count": 1, "price_fairness_score": null, "resale_liquidity_score": 67, "listing_score": 70}, {"source": "suumo", "property_type": "shinchiku", "url": "https://suumo.jp/ms/shinchiku/tokyo/sc_minato/nc_67731397/", "name": "ブランズシティ品川テラス", "price_man": 9470, "price_max_man": 13610, "address": "港区港南４", "station_line": "ＪＲ山手線/品川 徒歩13分", "walk_min": 13, "area_m2": null, "area_max_m2": null, "layout": "2LDK～4LDK", "delivery_date": "2027年1月下旬予定", "total_units": 216, "floor_total": 14, "list_ward_roman": "minato", "built_str": "", "built_year": null, "floor_position": null, "floor_structure": null, "ownership": "定期借地権付きレジデンス】誕生", "duplicate_count": 1, "latitude": 35.6301291, "longitude": 139.7507521, "ss_sumai_surfin_url": "https://www.sumai-surfin.com/re/49101/", "ss_profit_pct": 94, "ss_address": "東京都港区港南４－２９－５", "ss_favorite_count": 109, "ss_lookup_status": "found", "ss_sim_base_price": 6000, "ss_purchase_judgment": "条件付きで値上がりが期待できます", "geocode_confidence": "high", "hazard_info": "{\"flood\": false, \"sediment\": false, \"storm_surge\": false, \"tsunami\": false, \"liquefaction\": false, \"inland_water\": false, \"building_collapse\": 1, \"fire\": 1, \"combined\": 1}", "commute_info": "{\"playground\": {\"minutes\": 20, \"summary\": \"Google Maps経路 (朝9:00到着)\", \"calculatedAt\": \"2026-03-25T06:29:41Z\", \"source\": \"gmaps\"}, \"m3career\": {\"minutes\": 18, \"summary\": \"Google Maps経路 (朝9:00到着)\", \"calculatedAt\": \"2026-03-25T06:29:41Z\", \"source\": \"gmaps\"}}", "is_new": false, "is_new_building": false, "price_history": [{"date": "2026-03-25", "price_man": 9470}], "first_seen_at": "2026-03-25", "competing_listings_count": 1, "price_fairness_score": null, "resale_liquidity_score": 72, "listing_score": 78}, {"source": "suumo", "property_type": "shinchiku", "url": "https://suumo.jp/ms/shinchiku/tokyo/sc_minato/nc_67731846/", "name": "ブランズシティ品川ルネ キャナル", "price_man": 12000, "price_max_man": 19800, "address": "港区港南４", "station_line": "ＪＲ山手線/品川 徒歩14分", "walk_min": 14, "area_m2": null, "area_max_m2": null, "layout": "1LDK+S（納戸）～4LDK", "delivery_date": "2026年12月下旬予定", "total_units": 233, "floor_total": null, "list_ward_roman": "minato", "built_str": "", "built_year": null, "floor_position": null, "floor_structure": null, "ownership": null, "duplicate_count": 1, "latitude": 35.6301291, "longitude": 139.7507521, "ss_sumai_surfin_url": "https://www.sumai-surfin.com/re/48469/", "ss_profit_pct": 83, "ss_address": "東京都港区港南４－２０－１", "ss_favorite_count": 129, "ss_lookup_status": "found", "ss_sim_base_price": 6000, "ss_purchase_judgment": "条件付きで値上がりが期待できます", "geocode_confidence": "high", "hazard_info": "{\"flood\": false, \"sediment\": false, \"storm_surge\": false, \"tsunami\": false, \"liquefaction\": false, \"inland_water\": false, \"building_collapse\": 1, \"fire\": 1, \"combined\": 1}", "commute_info": "{\"playground\": {\"minutes\": 22, \"summary\": \"Google Maps経路 (朝9:00到着)\", \"calculatedAt\": \"2026-03-25T06:29:41Z\", \"source\": \"gmaps\"}, \"m3career\": {\"minutes\": 18, \"summary\": \"Google Maps経路 (朝9:00到着)\", \"calculatedAt\": \"2026-03-25T06:29:41Z\", \"source\": \"gmaps\"}}", "is_new": false, "is_new_building": false, "price_history": [{"date": "2026-03-25", "price_man": 11800}, {"date": "2026-03-25", "price_man": 12000}], "first_seen_at": "2026-03-15", "competing_listings_count": 1, "price_fairness_score": null, "resale_liquidity_score": 72, "listing_score": 75}, {"source": "suumo", "property_type": "shinchiku", "url": "https://suumo.jp/ms/shinchiku/tokyo/sc_arakawa/nc_67733049/", "name": "クレヴィア町屋レジデンス", "price_man": null, "price_max_man": null, "address": "荒川区荒川４", "station_line": "東京メトロ千代田線/町屋 徒歩10分", "walk_min": 10, "area_m2": 109.0, "area_max_m2": 55.0, "layout": "1LDK+S（納戸）～4LDK", "delivery_date": "2027年10月下旬予定", "total_units": null, "floor_total": null, "list_ward_roman": "arakawa", "built_str": "", "built_year": null, "floor_position": null, "floor_structure": null, "ownership": null, "duplicate_count": 1, "latitude": 35.737404, "longitude": 139.7772062, "ss_sumai_surfin_url": "https://www.sumai-surfin.com/re/49876/", "ss_profit_pct": 78, "ss_address": "東京都荒川区荒川４－４－４", "ss_favorite_count": 46, "ss_lookup_status": "found", "ss_sim_base_price": 6000, "ss_purchase_judgment": "条件付きで値上がりが期待できます", "geocode_confidence": "high", "hazard_info": "{\"flood\": true, \"sediment\": false, \"storm_surge\": false, \"tsunami\": false, \"liquefaction\": false, \"inland_water\": false, \"building_collapse\": 4, \"fire\": 4, \"combined\": 4}", "commute_info": "{\"playground\": {\"minutes\": 40, \"summary\": \"Google Maps経路 (朝9:00到着)\", \"calculatedAt\": \"2026-03-25T06:29:41Z\", \"source\": \"gmaps\"}, \"m3career\": {\"minutes\": 35, \"summary\": \"Google Maps経路 (朝9:00到着)\", \"calculatedAt\": \"2026-03-25T06:29:41Z\", \"source\": \"gmaps\"}}", "is_new": false, "is_new_building": false, "price_history": [], "first_seen_at": "2026-03-15", "competing_listings_count": 1, "price_fairness_score": null, "resale_liquidity_score": 50, "listing_score": 55}, {"source": "suumo", "property_type": "shinchiku", "url": "https://suumo.jp/ms/shinchiku/tokyo/sc_koto/nc_67730638/", "name": "クレストプライムシティ南砂", "price_man": null, "price_max_man": null, "address": "江東区南砂３", "station_line": "東京メトロ東西線/南砂町 徒歩1分", "walk_min": 1, "area_m2": null, "area_max_m2": null, "layout": "3LDK", "delivery_date": "2027年4月下旬予定", "total_units": 396, "floor_total": null, "list_ward_roman": "koto", "built_str": "", "built_year": null, "floor_position": null, "floor_structure": null, "ownership": null, "duplicate_count": 1, "ss_sumai_surfin_url": "https://www.sumai-surfin.com/re/48250/", "ss_profit_pct": 77, "ss_address": "東京都江東区南砂３－１１－１１８", "ss_favorite_count": 70, "ss_lookup_status": "found", "ss_sim_base_price": 6000, "ss_purchase_judgment": "条件付きで値上がりが期待できます", "commute_info": "{\"playground\": {\"minutes\": 30, \"summary\": \"Google Maps経路 (朝9:00到着)\", \"calculatedAt\": \"2026-03-25T06:29:41Z\", \"source\": \"gmaps\"}, \"m3career\": {\"minutes\": 35, \"summary\": \"Google Maps経路 (朝9:00到着)\", \"calculatedAt\": \"2026-03-25T06:29:41Z\", \"source\": \"gmaps\"}}", "is_new": false, "is_new_building": false, "price_history": [], "first_seen_at": "2026-02-25", "competing_listings_count": 1, "price_fairness_score": null, "resale_liquidity_score": 85, "listing_score": 72}, {"source": "suumo", "property_type": "shinchiku", "url": "https://suumo.jp/ms/shinchiku/tokyo/sc_minato/nc_67729887/", "name": "シエリアタワー南麻布", "price_man": null, "price_max_man": null, "address": "港区南麻布３", "station_line": "東京メトロ南北線/白金高輪 徒歩9分", "walk_min": 9, "area_m2": null, "area_max_m2": null, "layout": "2LDK～3LDK", "delivery_date": "2027年4月下旬予定", "total_units": null, "floor_total": null, "list_ward_roman": "minato", "built_str": "", "built_year": null, "floor_position": null, "floor_structure": null, "ownership": null, "duplicate_count": 1, "ss_sumai_surfin_url": "https://www.sumai-surfin.com/re/48410/", "ss_profit_pct": 91, "ss_address": "東京都港区南麻布３－１４５－３", "ss_favorite_count": 101, "ss_lookup_status": "found", "ss_sim_base_price": 6000, "ss_purchase_judgment": "条件付きで値上がりが期待できます", "commute_info": "{\"playground\": {\"minutes\": 18, \"summary\": \"Google Maps経路 (朝9:00到着)\", \"calculatedAt\": \"2026-03-25T06:29:41Z\", \"source\": \"gmaps\"}, \"m3career\": {\"minutes\": 12, \"summary\": \"Google Maps経路 (朝9:00到着)\", \"calculatedAt\": \"2026-03-25T06:29:41Z\", \"source\": \"gmaps\"}}", "is_new": false, "is_new_building": false, "price_history": [], "first_seen_at": "2026-03-15", "competing_listings_count": 1, "price_fairness_score": null, "resale_liquidity_score": 67, "listing_score": 82}, {"source": "suumo", "property_type": "shinchiku", "url": "https://suumo.jp/ms/shinchiku/tokyo/sc_koto/nc_67732378/", "name": "ザ・パークハウス 門前仲町", "price_man": 11030, "price_max_man": 13300, "address": "江東区佐賀１", "station_line": "東京メトロ東西線/門前仲町 徒歩8分", "walk_min": 8, "area_m2": null, "area_max_m2": null, "layout": "2LDK・", "delivery_date": "2028年1月下旬予定", "total_units": 240, "floor_total": null, "list_ward_roman": "koto", "built_str": "", "built_year": null, "floor_position": null, "floor_structure": null, "ownership": "金含む", "duplicate_count": 1, "ss_sumai_surfin_url": "https://www.sumai-surfin.com/re/49051/", "ss_profit_pct": 94, "ss_address": "東京都江東区佐賀１－１６－１", "ss_favorite_count": 61, "ss_lookup_status": "found", "ss_sim_base_price": 6000, "ss_purchase_judgment": "条件付きで値上がりが期待できます", "commute_info": "{\"playground\": {\"minutes\": 24, \"summary\": \"Google Maps経路 (朝9:00到着)\", \"calculatedAt\": \"2026-03-25T06:29:41Z\", \"source\": \"gmaps\"}, \"m3career\": {\"minutes\": 22, \"summary\": \"Google Maps経路 (朝9:00到着)\", \"calculatedAt\": \"2026-03-25T06:29:41Z\", \"source\": \"gmaps\"}}", "is_new": false, "is_new_building": false, "price_history": [{"date": "2026-03-25", "price_man": 11030}], "first_seen_at": "2026-02-25", "competing_listings_count": 1, "price_fairness_score": null, "resale_liquidity_score": 68, "listing_score": 79}, {"source": "suumo", "property_type": "shinchiku", "url": "https://suumo.jp/ms/shinchiku/tokyo/sc_chuo/nc_67735382/", "name": "クリオ日本橋人形町", "price_man": null, "price_max_man": null, "address": "中央区日本橋人形町２", "station_line": "東京メトロ半蔵門線/水天宮前 徒歩3分", "walk_min": 3, "area_m2": 44.0, "area_max_m2": 92.0, "layout": "2LDK・", "delivery_date": "2027年9月下旬予定", "total_units": null, "floor_total": null, "list_ward_roman": "chuo", "built_str": "", "built_year": null, "floor_position": null, "floor_structure": null, "ownership": null, "duplicate_count": 1, "ss_sumai_surfin_url": "https://www.sumai-surfin.com/re/49633/", "ss_profit_pct": 86, "ss_address": "東京都中央区日本橋人形町２－１５－９、", "ss_favorite_count": 56, "ss_lookup_status": "found", "ss_sim_base_price": 6000, "ss_purchase_judgment": "条件付きで値上がりが期待できます", "commute_info": "{\"playground\": {\"minutes\": 18, \"summary\": \"Google Maps経路 (朝9:00到着)\", \"calculatedAt\": \"2026-03-25T06:29:41Z\", \"source\": \"gmaps\"}, \"m3career\": {\"minutes\": 22, \"summary\": \"Google Maps経路 (朝9:00到着)\", \"calculatedAt\": \"2026-03-25T06:29:41Z\", \"source\": \"gmaps\"}}", "is_new": false, "is_new_building": false, "price_history": [], "first_seen_at": "2026-02-25", "competing_listings_count": 1, "price_fairness_score": null, "resale_liquidity_score": 83, "listing_score": 86}, {"source": "suumo", "property_type": "shinchiku", "url": "https://suumo.jp/ms/shinchiku/tokyo/sc_shinjuku/nc_67734389/", "name": "Brillia(ブリリア)西新宿", "price_man": null, "price_max_man": null, "address": "新宿区西新宿８", "station_line": "東京メトロ丸ノ内線/西新宿 徒歩5分", "walk_min": 5, "area_m2": null, "area_max_m2": null, "layout": "1LDK～3LDK", "delivery_date": "2027年11月下旬予定", "total_units": 71, "floor_total": null, "list_ward_roman": "shinjuku", "built_str": "", "built_year": null, "floor_position": null, "floor_structure": null, "ownership": "一般定期借地権)）", "duplicate_count": 1, "ss_sumai_surfin_url": "https://www.sumai-surfin.com/re/49729/", "ss_profit_pct": 92, "ss_address": "東京都新宿区西新宿８－１４４－２", "ss_favorite_count": 54, "ss_lookup_status": "found", "ss_sim_base_price": 6000, "ss_purchase_judgment": "条件付きで値上がりが期待できます", "commute_info": "{\"playground\": {\"minutes\": 20, \"summary\": \"Google Maps経路 (朝9:00到着)\", \"calculatedAt\": \"2026-03-25T06:29:41Z\", \"source\": \"gmaps\"}, \"m3career\": {\"minutes\": 20, \"summary\": \"Google Maps経路 (朝9:00到着)\", \"calculatedAt\": \"2026-03-25T06:29:41Z\", \"source\": \"gmaps\"}}", "is_new": false, "is_new_building": false, "price_history": [], "first_seen_at": "2026-02-25", "competing_listings_count": 1, "price_fairness_score": null, "resale_liquidity_score": 77, "listing_score": 86}, {"source": "suumo", "property_type": "shinchiku", "url": "https://suumo.jp/ms/shinchiku/tokyo/sc_chiyoda/nc_67734645/", "name": "パークコート千代田麹町", "price_man": null, "price_max_man": null, "address": "千代田区麹町１", "station_line": "東京メトロ半蔵門線/半蔵門 徒歩2分", "walk_min": 2, "area_m2": null, "area_max_m2": null, "layout": "1DK～3LDK", "delivery_date": "2028年4月下旬予定", "total_units": null, "floor_total": null, "list_ward_roman": "chiyoda", "built_str": "", "built_year": null, "floor_position": null, "floor_structure": null, "ownership": "金含む／予定", "duplicate_count": 1, "latitude": 35.6833509, "longitude": 139.7437121, "ss_sumai_surfin_url": "https://www.sumai-surfin.com/re/49690/", "ss_profit_pct": 92, "ss_address": "東京都千代田区麹町１－５－２", "ss_favorite_count": 54, "ss_lookup_status": "found", "ss_sim_base_price": 6000, "ss_purchase_judgment": "条件付きで値上がりが期待できます", "geocode_confidence": "high", "hazard_info": "{\"flood\": false, \"sediment\": false, \"storm_surge\": false, \"tsunami\": false, \"liquefaction\": false, \"inland_water\": false, \"building_collapse\": 1, \"fire\": 1, \"combined\": 1}", "commute_info": "{\"playground\": {\"minutes\": 3, \"summary\": \"Google Maps経路 (朝9:00到着)\", \"calculatedAt\": \"2026-03-25T06:29:41Z\", \"source\": \"gmaps\"}, \"m3career\": {\"minutes\": 9, \"summary\": \"Google Maps経路 (朝9:00到着)\", \"calculatedAt\": \"2026-03-25T06:29:41Z\", \"source\": \"gmaps\"}}", "is_new": false, "is_new_building": false, "price_history": [], "first_seen_at": "2026-03-25", "competing_listings_count": 1, "price_fairness_score": null, "resale_liquidity_score": 83, "listing_score": 81}, {"source": "suumo", "property_type": "shinchiku", "url": "https://suumo.jp/ms/shinchiku/tokyo/sc_minato/nc_67733584/", "name": "パークコート麻布十番東京 ザ タワー ノース／ザ タワー サウス", "price_man": null, "price_max_man": null, "address": "港区三田１", "station_line": "都営大江戸線/麻布十番 徒歩2分", "walk_min": 2, "area_m2": null, "area_max_m2": null, "layout": "1LDK～4LDK", "delivery_date": "2030年6月下旬予定、2029年10月下旬予定", "total_units": null, "floor_total": 34, "list_ward_roman": "minato", "built_str": "", "built_year": null, "floor_position": null, "floor_structure": null, "ownership": null, "duplicate_count": 1, "latitude": 35.6540335, "longitude": 139.7441783, "ss_lookup_status": "not_found", "geocode_confidence": "high", "hazard_info": "{\"flood\": false, \"sediment\": false, \"storm_surge\": false, \"tsunami\": false, \"liquefaction\": false, \"inland_water\": false, \"building_collapse\": 1, \"fire\": 1, \"combined\": 1}", "commute_info": "{\"playground\": {\"minutes\": 16, \"summary\": \"Google Maps経路 (朝9:00到着)\", \"calculatedAt\": \"2026-03-25T06:29:41Z\", \"source\": \"gmaps\"}, \"m3career\": {\"minutes\": 8, \"summary\": \"Google Maps経路 (朝9:00到着)\", \"calculatedAt\": \"2026-03-25T06:29:41Z\", \"source\": \"gmaps\"}}", "is_new": false, "is_new_building": false, "price_history": [], "first_seen_at": "2026-02-25", "competing_listings_count": 1, "price_fairness_score": null, "resale_liquidity_score": 89, "listing_score": 79}, {"source": "suumo", "property_type": "shinchiku", "url": "https://suumo.jp/ms/shinchiku/tokyo/sc_bunkyo/nc_67733307/", "name": "ザ・パークハウス 文京白山レジデンス", "price_man": null, "price_max_man": null, "address": "文京区白山５", "station_line": "都営三田線/千石 徒歩4分", "walk_min": 4, "area_m2": null, "area_max_m2": null, "layout": "1LDK～3LDK", "delivery_date": "2028年5月中旬予定", "total_units": null, "floor_total": null, "list_ward_roman": "bunkyo", "built_str": "", "built_year": null, "floor_position": null, "floor_structure": null, "ownership": null, "duplicate_count": 1, "ss_sumai_surfin_url": "https://www.sumai-surfin.com/re/49682/", "ss_profit_pct": 78, "ss_address": "東京都文京区白山５－１２－４４、", "ss_favorite_count": 49, "ss_lookup_status": "found", "ss_sim_base_price": 6000, "ss_purchase_judgment": "条件付きで値上がりが期待できます", "commute_info": "{\"playground\": {\"minutes\": 20, \"summary\": \"Google Maps経路 (朝9:00到着)\", \"calculatedAt\": \"2026-03-25T06:29:41Z\", \"source\": \"gmaps\"}, \"m3career\": {\"minutes\": 26, \"summary\": \"Google Maps経路 (朝9:00到着)\", \"calculatedAt\": \"2026-03-25T06:29:41Z\", \"source\": \"gmaps\"}}", "is_new": false, "is_new_building": false, "price_history": [], "first_seen_at": "2026-02-25", "competing_listings_count": 1, "price_fairness_score": null, "resale_liquidity_score": 82, "listing_score": 78}, {"source": "suumo", "property_type": "shinchiku", "url": "https://suumo.jp/ms/shinchiku/tokyo/sc_nerima/nc_67736223/", "name": "ベルジュール氷川台", "price_man": 7898, "price_max_man": 9198, "address": "練馬区氷川台４", "station_line": "東京メトロ有楽町線/氷川台 徒歩7分", "walk_min": 7, "area_m2": null, "area_max_m2": null, "layout": "2LDK+S（納戸）・", "delivery_date": "2027年1月下旬予定", "total_units": null, "floor_total": 1, "list_ward_roman": "nerima", "built_str": "", "built_year": null, "floor_position": null, "floor_structure": null, "ownership": null, "duplicate_count": 1, "latitude": 35.7498203, "longitude": 139.6650562, "ss_sumai_surfin_url": "https://www.sumai-surfin.com/re/49376/", "ss_profit_pct": 55, "ss_address": "東京都練馬区氷川台４－８４－３９", "ss_favorite_count": 50, "ss_lookup_status": "found", "ss_sim_base_price": 6000, "ss_purchase_judgment": "条件付きで値上がりが期待できます", "geocode_confidence": "high", "hazard_info": "{\"flood\": true, \"sediment\": false, \"storm_surge\": false, \"tsunami\": false, \"liquefaction\": false, \"inland_water\": false, \"building_collapse\": 2, \"fire\": 1, \"combined\": 1}", "commute_info": "{\"playground\": {\"minutes\": 45, \"summary\": \"Google Maps経路 (朝9:00到着)\", \"calculatedAt\": \"2026-03-25T06:29:41Z\", \"source\": \"gmaps\"}, \"m3career\": {\"minutes\": 45, \"summary\": \"Google Maps経路 (朝9:00到着)\", \"calculatedAt\": \"2026-03-25T06:29:41Z\", \"source\": \"gmaps\"}}", "is_new": false, "is_new_building": false, "price_history": [{"date": "2026-03-25", "price_man": 6998}, {"date": "2026-03-26", "price_man": 7898}], "first_seen_at": "2026-02-25", "competing_listings_count": 1, "price_fairness_score": null, "resale_liquidity_score": 55, "listing_score": 50}, {"source": "suumo", "property_type": "shinchiku", "url": "https://suumo.jp/ms/shinchiku/tokyo/sc_adachi/nc_67725752/", "name": "シティタワー綾瀬", "price_man": 9900, "price_max_man": 14100, "address": "足立区綾瀬３", "station_line": "東京メトロ千代田線/綾瀬 徒歩1分", "walk_min": 1, "area_m2": null, "area_max_m2": null, "layout": "2LDK～3LDK", "delivery_date": "2027年4月下旬予定", "total_units": null, "floor_total": null, "list_ward_roman": "adachi", "built_str": "", "built_year": null, "floor_position": null, "floor_structure": null, "ownership": null, "duplicate_count": 1, "ss_sumai_surfin_url": "https://www.sumai-surfin.com/re/46095/", "ss_profit_pct": 46, "ss_address": "東京都足立区綾瀬３－４－４", "ss_favorite_count": 55, "ss_lookup_status": "found", "ss_sim_base_price": 6000, "ss_purchase_judgment": "条件付きで値上がりが期待できます", "commute_info": "{\"playground\": {\"minutes\": 45, \"summary\": \"Google Maps経路 (朝9:00到着)\", \"calculatedAt\": \"2026-03-25T06:29:41Z\", \"source\": \"gmaps\"}, \"m3career\": {\"minutes\": 49, \"summary\": \"Google Maps経路 (朝9:00到着)\", \"calculatedAt\": \"2026-03-25T06:29:41Z\", \"source\": \"gmaps\"}}", "is_new": false, "is_new_building": false, "price_history": [{"date": "2026-03-25", "price_man": 10400}, {"date": "2026-03-27", "price_man": 9900}], "first_seen_at": "2026-03-25", "competing_listings_count": 1, "price_fairness_score": null, "resale_liquidity_score": 67, "listing_score": 49}, {"source": "suumo", "property_type": "shinchiku", "url": "https://suumo.jp/ms/shinchiku/tokyo/sc_koto/nc_67725228/", "name": "シティテラス南砂", "price_man": 9900, "price_max_man": 13500, "address": "江東区南砂４", "station_line": "東京メトロ東西線/南砂町 徒歩7分", "walk_min": 7, "area_m2": null, "area_max_m2": null, "layout": "3LD・K", "delivery_date": "2027年4月下旬予定", "total_units": 150, "floor_total": null, "list_ward_roman": "koto", "built_str": "", "built_year": null, "floor_position": null, "floor_structure": null, "ownership": null, "duplicate_count": 1, "ss_sumai_surfin_url": "https://www.sumai-surfin.com/re/46394/", "ss_address": "東京都江東区南砂４－２６１－１０外", "ss_favorite_count": 98, "ss_lookup_status": "found", "ss_sim_base_price": 11300, "ss_surrounding_properties": "[{\"name\": \"ニューライズシティ東京ベイハイライズ\", \"url\": \"https://www.sumai-surfin.com/re/1549/\", \"appreciation_rate\": 115.3, \"oki_price_70m2\": 7350}, {\"name\": \"グランエスタ（ファイブスター）\", \"url\": \"https://www.sumai-surfin.com/re/1529/\", \"appreciation_rate\": 110.3, \"oki_price_70m2\": 7910}, {\"name\": \"クレストフォルム東京アヴァンセ\", \"url\": \"https://www.sumai-surfin.com/re/403/\", \"appreciation_rate\": 109.2, \"oki_price_70m2\": 6930}, {\"name\": \"メロディーハイム南砂町フェイシア\", \"url\": \"https://www.sumai-surfin.com/re/1158/\", \"appreciation_rate\": 103.8, \"oki_price_70m2\": 6650}, {\"name\": \"エムステージウエスティア\", \"url\": \"https://www.sumai-surfin.com/re/13700/\", \"appreciation_rate\": 102.0, \"oki_price_70m2\": 6930}, {\"name\": \"クレストフォルム南砂仙台堀川公園\", \"url\": \"https://www.sumai-surfin.com/re/1919/\", \"appreciation_rate\": 91.1, \"oki_price_70m2\": 5880}, {\"name\": \"オーベルグランディオ砂町水辺公園\", \"url\": \"https://www.sumai-surfin.com/re/1534/\", \"appreciation_rate\": 90.2, \"oki_price_70m2\": 5530}, {\"name\": \"クレヴィア南砂\", \"url\": \"https://www.sumai-surfin.com/re/30257/\", \"appreciation_rate\": 89.5, \"oki_price_70m2\": 8190}, {\"name\": \"フェルモ南砂\", \"url\": \"https://www.sumai-surfin.com/re/28636/\", \"appreciation_rate\": 81.4, \"oki_price_70m2\": 7630}, {\"name\": \"グランシティ東陽町II\", \"url\": \"https://www.sumai-surfin.com/re/276/\", \"appreciation_rate\": 81.0, \"oki_price_70m2\": 6440}]", "ss_purchase_judgment": "条件付きで値上がりが期待できます", "commute_info": "{\"playground\": {\"minutes\": 28, \"summary\": \"Google Maps経路 (朝9:00到着)\", \"calculatedAt\": \"2026-03-25T06:29:41Z\", \"source\": \"gmaps\"}, \"m3career\": {\"minutes\": 35, \"summary\": \"Google Maps経路 (朝9:00到着)\", \"calculatedAt\": \"2026-03-25T06:29:41Z\", \"source\": \"gmaps\"}}", "is_new": false, "is_new_building": false, "price_history": [{"date": "2026-03-25", "price_man": 11300}, {"date": "2026-03-27", "price_man": 9900}], "first_seen_at": "2026-02-25", "competing_listings_count": 1, "price_fairness_score": null, "resale_liquidity_score": 71, "listing_score": 63}, {"source": "suumo", "property_type": "shinchiku", "url": "https://suumo.jp/ms/shinchiku/tokyo/sc_edogawa/nc_67730181/", "name": "サンクレイドル葛西ステーションウィズ", "price_man": null, "price_max_man": null, "address": "江戸川区中葛西５", "station_line": "東京メトロ東西線/葛西 徒歩4分", "walk_min": 4, "area_m2": null, "area_max_m2": null, "layout": "2LDK+S（納戸）・", "delivery_date": "2026年11月下旬予定", "total_units": null, "floor_total": null, "list_ward_roman": "edogawa", "built_str": "", "built_year": null, "floor_position": null, "floor_structure": null, "ownership": null, "duplicate_count": 1, "latitude": 35.6638877, "longitude": 139.8687474, "ss_sumai_surfin_url": "https://www.sumai-surfin.com/re/49377/", "ss_profit_pct": 49, "ss_address": "東京都江戸川区中葛西５－３７－１", "ss_favorite_count": 50, "ss_lookup_status": "found", "ss_sim_base_price": 6000, "ss_purchase_judgment": "条件付きで値上がりが期待できます", "geocode_confidence": "high", "hazard_info": "{\"flood\": true, \"sediment\": false, \"storm_surge\": true, \"tsunami\": false, \"liquefaction\": false, \"inland_water\": false, \"building_collapse\": 2, \"fire\": 2, \"combined\": 2}", "commute_info": "{\"playground\": {\"minutes\": 40, \"summary\": \"Google Maps経路 (朝9:00到着)\", \"calculatedAt\": \"2026-03-25T06:29:41Z\", \"source\": \"gmaps\"}, \"m3career\": {\"minutes\": 35, \"summary\": \"Google Maps経路 (朝9:00到着)\", \"calculatedAt\": \"2026-03-25T06:29:41Z\", \"source\": \"gmaps\"}}", "is_new": false, "is_new_building": false, "price_history": [], "first_seen_at": "2026-02-25", "competing_listings_count": 1, "price_fairness_score": null, "resale_liquidity_score": 61, "listing_score": 47}, {"source": "suumo", "property_type": "shinchiku", "url": "https://suumo.jp/ms/shinchiku/tokyo/sc_chuo/nc_67734604/", "name": "パークホームズ日本橋人形町三丁目", "price_man": null, "price_max_man": null, "address": "中央区日本橋人形町３", "station_line": "東京メトロ日比谷線/人形町 徒歩2分", "walk_min": 2, "area_m2": null, "area_max_m2": null, "layout": "1LDK～3LDK", "delivery_date": "2027年6月下旬予定", "total_units": null, "floor_total": null, "list_ward_roman": "chuo", "built_str": "", "built_year": null, "floor_position": null, "floor_structure": null, "ownership": null, "duplicate_count": 1, "ss_sumai_surfin_url": "https://www.sumai-surfin.com/re/49573/", "ss_profit_pct": 91, "ss_address": "東京都中央区日本橋人形町３－１－６", "ss_favorite_count": 57, "ss_lookup_status": "found", "ss_sim_base_price": 6000, "ss_purchase_judgment": "条件付きで値上がりが期待できます", "commute_info": "{\"playground\": {\"minutes\": 20, \"summary\": \"Google Maps経路 (朝9:00到着)\", \"calculatedAt\": \"2026-03-25T06:29:41Z\", \"source\": \"gmaps\"}, \"m3career\": {\"minutes\": 18, \"summary\": \"Google Maps経路 (朝9:00到着)\", \"calculatedAt\": \"2026-03-25T06:29:41Z\", \"source\": \"gmaps\"}}", "is_new": false, "is_new_building": false, "price_history": [], "first_seen_at": "2026-03-11", "competing_listings_count": 1, "price_fairness_score": null, "resale_liquidity_score": 89, "listing_score": 90}, {"source": "suumo", "property_type": "shinchiku", "url": "https://suumo.jp/ms/shinchiku/tokyo/sc_suginami/nc_67735099/", "name": "パークホームズ東高円寺", "price_man": 9000, "price_max_man": 17000, "address": "杉並区高円寺南１", "station_line": "東京メトロ丸ノ内線/東高円寺 徒歩3分", "walk_min": 3, "area_m2": null, "area_max_m2": null, "layout": "1LDK～3LDK", "delivery_date": "2027年4月下旬予定", "total_units": null, "floor_total": null, "list_ward_roman": "suginami", "built_str": "", "built_year": null, "floor_position": null, "floor_structure": null, "ownership": null, "duplicate_count": 1, "latitude": 35.700703, "longitude": 139.639985, "ss_sumai_surfin_url": "https://www.sumai-surfin.com/re/49707/", "ss_profit_pct": 67, "ss_address": "東京都杉並区高円寺南１－４５４－７外", "ss_favorite_count": 50, "ss_lookup_status": "found", "ss_sim_base_price": 6000, "ss_purchase_judgment": "条件付きで値上がりが期待できます", "geocode_confidence": "high", "hazard_info": "{\"flood\": false, \"sediment\": false, \"storm_surge\": false, \"tsunami\": false, \"liquefaction\": false, \"inland_water\": false, \"building_collapse\": 2, \"fire\": 4, \"combined\": 4}", "commute_info": "{\"playground\": {\"minutes\": 35, \"summary\": \"Google Maps経路 (朝9:00到着)\", \"calculatedAt\": \"2026-03-25T06:29:41Z\", \"source\": \"gmaps\"}, \"m3career\": {\"minutes\": 30, \"summary\": \"Google Maps経路 (朝9:00到着)\", \"calculatedAt\": \"2026-03-25T06:29:41Z\", \"source\": \"gmaps\"}}", "is_new": false, "is_new_building": false, "price_history": [{"date": "2026-03-25", "price_man": 9000}], "first_seen_at": "2026-02-25", "competing_listings_count": 1, "price_fairness_score": null, "resale_liquidity_score": 83, "listing_score": 64}, {"source": "suumo", "property_type": "shinchiku", "url": "https://suumo.jp/ms/shinchiku/tokyo/sc_chiyoda/nc_67734943/", "name": "ザ レジデンス 三番町", "price_man": null, "price_max_man": null, "address": "千代田区三番町", "station_line": "東京メトロ半蔵門線/半蔵門 徒歩8分", "walk_min": 8, "area_m2": 100.0, "area_max_m2": 100.0, "layout": "1LDK～3LDK", "delivery_date": "2028年8月下旬予定", "total_units": 124, "floor_total": null, "list_ward_roman": "chiyoda", "built_str": "", "built_year": null, "floor_position": null, "floor_structure": null, "ownership": null, "duplicate_count": 1, "latitude": 35.690557, "longitude": 139.743591, "ss_appreciation_rate": 88.7, "ss_sumai_surfin_url": "https://www.sumai-surfin.com/re/49645/", "ss_profit_pct": 81, "ss_address": "東京都千代田区三番町６－５", "ss_favorite_count": 49, "ss_lookup_status": "found", "ss_sim_base_price": 6000, "ss_purchase_judgment": "条件付きで値上がりが期待できます", "geocode_confidence": "high", "hazard_info": "{\"flood\": false, \"sediment\": false, \"storm_surge\": false, \"tsunami\": false, \"liquefaction\": false, \"inland_water\": false, \"building_collapse\": 1, \"fire\": 1, \"combined\": 1}", "commute_info": "{\"playground\": {\"minutes\": 2, \"summary\": \"Google Maps経路 (朝9:00到着)\", \"calculatedAt\": \"2026-03-25T06:29:41Z\", \"source\": \"gmaps\"}, \"m3career\": {\"minutes\": 12, \"summary\": \"Google Maps経路 (朝9:00到着)\", \"calculatedAt\": \"2026-03-25T06:29:41Z\", \"source\": \"gmaps\"}}", "is_new": false, "is_new_building": false, "price_history": [], "first_seen_at": "2026-02-25", "competing_listings_count": 1, "price_fairness_score": null, "resale_liquidity_score": 63, "listing_score": 77}, {"source": "suumo", "property_type": "shinchiku", "url": "https://suumo.jp/ms/shinchiku/tokyo/sc_minato/nc_67736125/", "name": "パークホームズ虎ノ門", "price_man": null, "price_max_man": null, "address": "港区西新橋３", "station_line": "東京メトロ銀座線/虎ノ門 徒歩6分", "walk_min": 6, "area_m2": 114.0, "area_max_m2": 114.0, "layout": "3LDK", "delivery_date": "2028年3月下旬予定", "total_units": 37, "floor_total": null, "list_ward_roman": "minato", "built_str": "", "built_year": null, "floor_position": null, "floor_structure": null, "ownership": null, "duplicate_count": 1, "ss_lookup_status": "not_found", "commute_info": "{\"playground\": {\"minutes\": 12, \"summary\": \"Google Maps経路 (朝9:00到着)\", \"calculatedAt\": \"2026-03-25T06:29:41Z\", \"source\": \"gmaps\"}, \"m3career\": {\"minutes\": 5, \"summary\": \"Google Maps経路 (朝9:00到着)\", \"calculatedAt\": \"2026-03-25T06:29:41Z\", \"source\": \"gmaps\"}}", "is_new": false, "is_new_building": false, "price_history": [], "first_seen_at": "2026-03-17", "competing_listings_count": 1, "price_fairness_score": null, "resale_liquidity_score": 66, "listing_score": 78}, {"source": "suumo", "property_type": "shinchiku", "url": "https://suumo.jp/ms/shinchiku/tokyo/sc_sumida/nc_67735095/", "name": "パークホームズ錦糸町北斎通り", "price_man": null, "price_max_man": null, "address": "墨田区亀沢４", "station_line": "ＪＲ総武線快速/錦糸町 徒歩8分", "walk_min": 8, "area_m2": null, "area_max_m2": null, "layout": "2LDK～3LDK", "delivery_date": "2027年6月下旬予定", "total_units": 31, "floor_total": null, "list_ward_roman": "sumida", "built_str": "", "built_year": null, "floor_position": null, "floor_structure": null, "ownership": null, "duplicate_count": 1, "ss_sumai_surfin_url": "https://www.sumai-surfin.com/re/49695/", "ss_profit_pct": 82, "ss_address": "東京都墨田区亀沢４－１２－４", "ss_favorite_count": 50, "ss_lookup_status": "found", "ss_sim_base_price": 6000, "ss_purchase_judgment": "条件付きで値上がりが期待できます", "commute_info": "{\"playground\": {\"minutes\": 26, \"summary\": \"Google Maps経路 (朝9:00到着)\", \"calculatedAt\": \"2026-03-25T06:29:41Z\", \"source\": \"gmaps\"}, \"m3career\": {\"minutes\": 28, \"summary\": \"Google Maps経路 (朝9:00到着)\", \"calculatedAt\": \"2026-03-25T06:29:41Z\", \"source\": \"gmaps\"}}", "is_new": false, "is_new_building": false, "price_history": [], "first_seen_at": "2026-02-25", "competing_listings_count": 1, "price_fairness_score": null, "resale_liquidity_score": 48, "listing_score": 68}, {"source": "suumo", "property_type": "shinchiku", "url": "https://suumo.jp/ms/shinchiku/tokyo/sc_shinjuku/nc_67734365/", "name": "プラウド四谷", "price_man": null, "price_max_man": null, "address": "新宿区四谷１", "station_line": "ＪＲ中央線/四ツ谷 徒歩3分", "walk_min": 3, "area_m2": 70.0, "area_max_m2": 70.0, "layout": "2LDK～3LDK", "delivery_date": "2027年3月下旬予定", "total_units": null, "floor_total": null, "list_ward_roman": "shinjuku", "built_str": "", "built_year": null, "floor_position": null, "floor_structure": null, "ownership": null, "duplicate_count": 1, "latitude": 35.6879723, "longitude": 139.7278928, "ss_appreciation_rate": 92.2, "ss_sumai_surfin_url": "https://www.sumai-surfin.com/re/49666/", "ss_profit_pct": 81, "ss_address": "東京都新宿区四谷１－９－７", "ss_favorite_count": 59, "ss_lookup_status": "found", "ss_sim_base_price": 6000, "ss_purchase_judgment": "条件付きで値上がりが期待できます", "geocode_confidence": "high", "hazard_info": "{\"flood\": false, \"sediment\": false, \"storm_surge\": false, \"tsunami\": false, \"liquefaction\": false, \"inland_water\": false, \"building_collapse\": 1, \"fire\": 1, \"combined\": 1}", "commute_info": "{\"playground\": {\"minutes\": 6, \"summary\": \"Google Maps経路 (朝9:00到着)\", \"calculatedAt\": \"2026-03-25T06:29:41Z\", \"source\": \"gmaps\"}, \"m3career\": {\"minutes\": 14, \"summary\": \"Google Maps経路 (朝9:00到着)\", \"calculatedAt\": \"2026-03-25T06:29:41Z\", \"source\": \"gmaps\"}}", "is_new": false, "is_new_building": false, "price_history": [], "first_seen_at": "2026-02-25", "competing_listings_count": 1, "price_fairness_score": null, "resale_liquidity_score": 88, "listing_score": 82}, {"source": "suumo", "property_type": "shinchiku", "url": "https://suumo.jp/ms/shinchiku/tokyo/sc_chiyoda/nc_67733803/", "name": "ザ・パークハウス 千代田三番町", "price_man": null, "price_max_man": null, "address": "千代田区三番町", "station_line": "東京メトロ半蔵門線/半蔵門 徒歩7分", "walk_min": 7, "area_m2": 107.0, "area_max_m2": 55.0, "layout": "3LDK", "delivery_date": "2027年10月下旬予定", "total_units": null, "floor_total": null, "list_ward_roman": "chiyoda", "built_str": "", "built_year": null, "floor_position": null, "floor_structure": null, "ownership": null, "duplicate_count": 1, "latitude": 35.690557, "longitude": 139.743591, "ss_sumai_surfin_url": "https://www.sumai-surfin.com/re/49135/", "ss_profit_pct": 81, "ss_address": "東京都千代田区三番町６－２", "ss_favorite_count": 47, "ss_lookup_status": "found", "ss_sim_base_price": 6000, "ss_purchase_judgment": "条件付きで値上がりが期待できます", "geocode_confidence": "high", "hazard_info": "{\"flood\": false, \"sediment\": false, \"storm_surge\": false, \"tsunami\": false, \"liquefaction\": false, \"inland_water\": false, \"building_collapse\": 1, \"fire\": 1, \"combined\": 1}", "commute_info": "{\"playground\": {\"minutes\": 3, \"summary\": \"Google Maps経路 (朝9:00到着)\", \"calculatedAt\": \"2026-03-25T06:29:41Z\", \"source\": \"gmaps\"}, \"m3career\": {\"minutes\": 12, \"summary\": \"Google Maps経路 (朝9:00到着)\", \"calculatedAt\": \"2026-03-25T06:29:41Z\", \"source\": \"gmaps\"}}", "is_new": false, "is_new_building": false, "price_history": [], "first_seen_at": "2026-03-17", "competing_listings_count": 1, "price_fairness_score": null, "resale_liquidity_score": 67, "listing_score": 73}, {"source": "suumo", "property_type": "shinchiku", "url": "https://suumo.jp/ms/shinchiku/tokyo/sc_minato/nc_67730114/", "name": "パークコート青山高樹町 ザ タワー", "price_man": null, "price_max_man": null, "address": "港区南青山６", "station_line": "東京メトロ銀座線/表参道 徒歩9分", "walk_min": 9, "area_m2": 40.0, "area_max_m2": 143.0, "layout": "2LDK", "delivery_date": "2026年10月上旬予定", "total_units": null, "floor_total": 21, "list_ward_roman": "minato", "built_str": "", "built_year": null, "floor_position": null, "floor_structure": null, "ownership": "一般定期借地権））", "duplicate_count": 1, "ss_sumai_surfin_url": "https://www.sumai-surfin.com/re/48318/", "ss_profit_pct": 99, "ss_address": "東京都港区南青山６－２５５", "ss_favorite_count": 131, "ss_lookup_status": "found", "ss_sim_base_price": 6000, "ss_purchase_judgment": "条件付きで値上がりが期待できます", "commute_info": "{\"playground\": {\"minutes\": 12, \"summary\": \"Google Maps経路 (朝9:00到着)\", \"calculatedAt\": \"2026-03-25T06:29:41Z\", \"source\": \"gmaps\"}, \"m3career\": {\"minutes\": 10, \"summary\": \"Google Maps経路 (朝9:00到着)\", \"calculatedAt\": \"2026-03-25T06:29:41Z\", \"source\": \"gmaps\"}}", "is_new": false, "is_new_building": false, "price_history": [], "first_seen_at": "2026-03-15", "competing_listings_count": 1, "price_fairness_score": null, "resale_liquidity_score": 65, "listing_score": 84}, {"source": "suumo", "property_type": "shinchiku", "url": "https://suumo.jp/ms/shinchiku/tokyo/sc_chiyoda/nc_67722499/", "name": "パークコート ザ・三番町ハウス", "price_man": null, "price_max_man": null, "address": "千代田区三番町", "station_line": "東京メトロ半蔵門線/半蔵門 徒歩8分", "walk_min": 8, "area_m2": null, "area_max_m2": null, "layout": "2LDK", "delivery_date": "2026年4月下旬予定", "total_units": 193, "floor_total": 18, "list_ward_roman": "chiyoda", "built_str": "", "built_year": null, "floor_position": null, "floor_structure": null, "ownership": "一般定期借地権））", "duplicate_count": 1, "latitude": 35.690557, "longitude": 139.743591, "ss_sumai_surfin_url": "https://www.sumai-surfin.com/re/46833/", "ss_profit_pct": 92, "ss_address": "東京都千代田区三番町２８－３ほか", "ss_favorite_count": 175, "ss_lookup_status": "found", "ss_sim_base_price": 6000, "ss_purchase_judgment": "条件付きで値上がりが期待できます", "geocode_confidence": "high", "hazard_info": "{\"flood\": false, \"sediment\": false, \"storm_surge\": false, \"tsunami\": false, \"liquefaction\": false, \"inland_water\": false, \"building_collapse\": 1, \"fire\": 1, \"combined\": 1}", "commute_info": "{\"playground\": {\"minutes\": 2, \"summary\": \"Google Maps経路 (朝9:00到着)\", \"calculatedAt\": \"2026-03-25T06:29:41Z\", \"source\": \"gmaps\"}, \"m3career\": {\"minutes\": 12, \"summary\": \"Google Maps経路 (朝9:00到着)\", \"calculatedAt\": \"2026-03-25T06:29:41Z\", \"source\": \"gmaps\"}}", "is_new": false, "is_new_building": false, "price_history": [], "first_seen_at": "2026-03-22", "competing_listings_count": 1, "price_fairness_score": null, "resale_liquidity_score": 65, "listing_score": 76}, {"source": "suumo", "property_type": "shinchiku", "url": "https://suumo.jp/ms/shinchiku/tokyo/sc_taito/nc_78735356/", "name": "クレヴィア上野入谷", "price_man": 10190, "price_max_man": 10190, "address": "東京都台東区下谷２", "station_line": "東京メトロ日比谷線/入谷 徒歩4分", "walk_min": 4, "area_m2": null, "area_max_m2": null, "layout": "2LDK", "delivery_date": "相談", "total_units": null, "floor_total": null, "list_ward_roman": "taito", "built_str": "", "built_year": null, "floor_position": null, "floor_structure": null, "ownership": null, "duplicate_count": 1, "ss_sumai_surfin_url": "https://www.sumai-surfin.com/re/47805/", "ss_address": "東京都台東区下谷２－４－４", "ss_favorite_count": 62, "ss_lookup_status": "found", "ss_sim_base_price": 6000, "ss_purchase_judgment": "条件付きで値上がりが期待できます", "commute_info": "{\"playground\": {\"minutes\": 24, \"summary\": \"Google Maps経路 (朝9:00到着)\", \"calculatedAt\": \"2026-03-25T06:29:41Z\", \"source\": \"gmaps\"}, \"m3career\": {\"minutes\": 24, \"summary\": \"Google Maps経路 (朝9:00到着)\", \"calculatedAt\": \"2026-03-25T06:29:41Z\", \"source\": \"gmaps\"}}", "reinfolib_market_data": "{\"ward\": \"台東区\", \"ward_median_m2_price\": 1138462, \"ward_mean_m2_price\": 1171466, \"price_ratio\": null, \"price_diff_man\": null, \"sample_count\": 59, \"match_tier\": 1, \"match_description\": \"台東区・2LDK\", \"trend\": \"down\", \"yoy_change_pct\": -0.4, \"quarterly_m2_prices\": [{\"quarter\": \"2024Q1\", \"median_m2_price\": 1000000, \"count\": 99}, {\"quarter\": \"2024Q2\", \"median_m2_price\": 1026786, \"count\": 100}, {\"quarter\": \"2024Q3\", \"median_m2_price\": 963636, \"count\": 97}, {\"quarter\": \"2024Q4\", \"median_m2_price\": 1090000, \"count\": 98}, {\"quarter\": \"2025Q1\", \"median_m2_price\": 1016667, \"count\": 98}, {\"quarter\": \"2025Q2\", \"median_m2_price\": 1000000, \"count\": 99}, {\"quarter\": \"2025Q3\", \"median_m2_price\": 960000, \"count\": 96}], \"yearly_m2_prices\": [{\"year\": \"2021\", \"median_m2_price\": 1000000, \"count\": 10}, {\"year\": \"2022\", \"median_m2_price\": 1077500, \"count\": 11}, {\"year\": \"2023\", \"median_m2_price\": 1066667, \"count\": 9}, {\"year\": \"2024\", \"median_m2_price\": 1100000, \"count\": 11}, {\"year\": \"2025\", \"median_m2_price\": 1171429, \"count\": 9}], \"same_building_transactions\": [], \"station\": null, \"data_source\": \"不動産情報ライブラリ（国土交通省）\"}", "estat_population_data": "{\"ward\": \"台東区\", \"latest_population\": 213550, \"latest_households\": 132860, \"pop_change_1yr_pct\": 0.9, \"pop_change_5yr_pct\": 5.8, \"population_history\": [{\"year\": \"2020\", \"population\": 211444}, {\"year\": \"2021\", \"population\": 206516}, {\"year\": \"2022\", \"population\": 206134}, {\"year\": \"2023\", \"population\": 211645}, {\"year\": \"2024\", \"population\": 213550}], \"household_history\": [{\"year\": \"2020\", \"households\": 128410}, {\"year\": \"2021\", \"households\": 127320}, {\"year\": \"2022\", \"households\": 128290}, {\"year\": \"2023\", \"households\": 131710}, {\"year\": \"2024\", \"households\": 132860}], \"data_source\": \"e-Stat 政府統計（総務省）住民基本台帳に基づく人口\", \"aging_rate_history\": [{\"year\": \"2000\", \"aging_rate\": 22.2}, {\"year\": \"2005\", \"aging_rate\": 23.0}, {\"year\": \"2010\", \"aging_rate\": 23.7}, {\"year\": \"2015\", \"aging_rate\": 24.3}, {\"year\": \"2020\", \"aging_rate\": 23.9}], \"latest_aging_rate\": 23.9, \"national_aging_history\": [{\"year\": \"2000\", \"aging_rate\": 17.3}, {\"year\": \"2005\", \"aging_rate\": 20.2}, {\"year\": \"2010\", \"aging_rate\": 23.0}, {\"year\": \"2015\", \"aging_rate\": 26.6}, {\"year\": \"2020\", \"aging_rate\": 28.6}], \"tokyo23_avg_aging_history\": [{\"year\": \"2000\", \"aging_rate\": 17.5}, {\"year\": \"2005\", \"aging_rate\": 18.9}, {\"year\": \"2010\", \"aging_rate\": 20.2}, {\"year\": \"2015\", \"aging_rate\": 21.4}, {\"year\": \"2020\", \"aging_rate\": 21.1}]}", "is_new": false, "is_new_building": false, "price_history": [{"date": "2026-03-25", "price_man": 10190}], "first_seen_at": "2026-03-22", "competing_listings_count": 1, "price_fairness_score": null, "resale_liquidity_score": 77, "listing_score": 76}, {"source": "suumo", "property_type": "shinchiku", "url": "https://suumo.jp/ms/shinchiku/tokyo/sc_chuo/nc_79105530/", "name": "ＨＡＲＵＭＩ　ＦＬＡＧ　ＰＡＲＫ　ＶＩＬＬＡＧＥ　Ｔ棟", "price_man": 11900, "price_max_man": 11900, "address": "東京都中央区晴海５", "station_line": "都営大江戸線/勝どき 徒歩15分", "walk_min": 15, "area_m2": null, "area_max_m2": null, "layout": "2LDK", "delivery_date": "相談", "total_units": null, "floor_total": null, "list_ward_roman": "chuo", "built_str": "", "built_year": null, "floor_position": null, "floor_structure": null, "ownership": null, "duplicate_count": 1, "latitude": 35.6498252, "longitude": 139.7731905, "ss_appreciation_rate": 107.7, "ss_sumai_surfin_url": "https://www.sumai-surfin.com/re/42281/", "ss_oki_price_70m2": 13440, "ss_address": "東京都中央区晴海５－６", "ss_favorite_count": 162, "ss_lookup_status": "found", "ss_sim_base_price": 14990, "ss_surrounding_properties": "[{\"name\": \"ＴＨＥ　ＴＯＫＹＯ　ＴＯＷＥＲＳ（ザ・トーキョー・タワーズ）\", \"url\": \"https://www.sumai-surfin.com/re/1973/\", \"appreciation_rate\": 160.6, \"oki_price_70m2\": 11550}, {\"name\": \"セザールアクアフロント勝どきイースト\", \"url\": \"https://www.sumai-surfin.com/re/16055/\", \"appreciation_rate\": 143.3, \"oki_price_70m2\": 9590}, {\"name\": \"セザールリバーサイド月島\", \"url\": \"https://www.sumai-surfin.com/re/16063/\", \"appreciation_rate\": 139.6, \"oki_price_70m2\": 9590}, {\"name\": \"ＨＡＲＵＭＩ　ＦＬＡＧ　ＳＥＡ　ＶＩＬＬＡＧＥ（Ａ～Ｅ棟）\", \"url\": \"https://www.sumai-surfin.com/re/42271/\", \"appreciation_rate\": 137.0, \"oki_price_70m2\": 14700}, {\"name\": \"プラネ勝どき\", \"url\": \"https://www.sumai-surfin.com/re/1039/\", \"appreciation_rate\": 125.2, \"oki_price_70m2\": 8960}, {\"name\": \"アルス勝どきコモーネ\", \"url\": \"https://www.sumai-surfin.com/re/13119/\", \"appreciation_rate\": 123.4, \"oki_price_70m2\": 9030}, {\"name\": \"セザールアクアフロント勝どきウエスト\", \"url\": \"https://www.sumai-surfin.com/re/16056/\", \"appreciation_rate\": 119.4, \"oki_price_70m2\": 8610}, {\"name\": \"アスコットパーク勝どき\", \"url\": \"https://www.sumai-surfin.com/re/2120/\", \"appreciation_rate\": 117.7, \"oki_price_70m2\": 10220}, {\"name\": \"晴海テラス\", \"url\": \"https://www.sumai-surfin.com/re/11144/\", \"appreciation_rate\": 115.6, \"oki_price_70m2\": 9590}, {\"name\": \"クレアシティ勝どきアットステーション\", \"url\": \"https://www.sumai-surfin.com/re/13817/\", \"appreciation_rate\": 114.2, \"oki_price_70m2\": 8680}]", "ss_purchase_judgment": "条件付きで値上がりが期待できます", "geocode_confidence": "high", "hazard_info": "{\"flood\": false, \"sediment\": false, \"storm_surge\": false, \"tsunami\": false, \"liquefaction\": false, \"inland_water\": false, \"building_collapse\": 1, \"fire\": 1, \"combined\": 1}", "commute_info": "{\"playground\": {\"minutes\": 18, \"summary\": \"Google Maps経路 (朝9:00到着)\", \"calculatedAt\": \"2026-03-25T06:29:41Z\", \"source\": \"gmaps\"}, \"m3career\": {\"minutes\": 12, \"summary\": \"Google Maps経路 (朝9:00到着)\", \"calculatedAt\": \"2026-03-25T06:29:41Z\", \"source\": \"gmaps\"}}", "reinfolib_market_data": "{\"ward\": \"中央区\", \"ward_median_m2_price\": 1669697, \"ward_mean_m2_price\": 1673121, \"price_ratio\": null, \"price_diff_man\": null, \"sample_count\": 78, \"match_tier\": 1, \"match_description\": \"中央区・2LDK\", \"trend\": \"flat\", \"yoy_change_pct\": 33.1, \"quarterly_m2_prices\": [{\"quarter\": \"2024Q1\", \"median_m2_price\": 1414973, \"count\": 100}, {\"quarter\": \"2024Q2\", \"median_m2_price\": 1288889, \"count\": 99}, {\"quarter\": \"2024Q3\", \"median_m2_price\": 1381818, \"count\": 99}, {\"quarter\": \"2024Q4\", \"median_m2_price\": 1633333, \"count\": 100}, {\"quarter\": \"2025Q1\", \"median_m2_price\": 1761616, \"count\": 100}, {\"quarter\": \"2025Q2\", \"median_m2_price\": 1857143, \"count\": 100}, {\"quarter\": \"2025Q3\", \"median_m2_price\": 1839744, \"count\": 100}], \"yearly_m2_prices\": [{\"year\": \"2021\", \"median_m2_price\": 1200000, \"count\": 19}, {\"year\": \"2022\", \"median_m2_price\": 1225000, \"count\": 20}, {\"year\": \"2023\", \"median_m2_price\": 1300000, \"count\": 20}, {\"year\": \"2024\", \"median_m2_price\": 1400000, \"count\": 21}, {\"year\": \"2025\", \"median_m2_price\": 1592857, \"count\": 19}], \"same_building_transactions\": [], \"station\": null, \"data_source\": \"不動産情報ライブラリ（国土交通省）\"}", "estat_population_data": "{\"ward\": \"中央区\", \"latest_population\": 187462, \"latest_households\": 101935, \"pop_change_1yr_pct\": 3.2, \"pop_change_5yr_pct\": 17.5, \"population_history\": [{\"year\": \"2020\", \"population\": 169179}, {\"year\": \"2021\", \"population\": 170504}, {\"year\": \"2022\", \"population\": 174924}, {\"year\": \"2023\", \"population\": 181653}, {\"year\": \"2024\", \"population\": 187462}], \"household_history\": [{\"year\": \"2020\", \"households\": 90240}, {\"year\": \"2021\", \"households\": 91830}, {\"year\": \"2022\", \"households\": 94750}, {\"year\": \"2023\", \"households\": 98930}, {\"year\": \"2024\", \"households\": 101935}], \"data_source\": \"e-Stat 政府統計（総務省）住民基本台帳に基づく人口\", \"aging_rate_history\": [{\"year\": \"2000\", \"aging_rate\": 19.5}, {\"year\": \"2005\", \"aging_rate\": 17.5}, {\"year\": \"2010\", \"aging_rate\": 16.2}, {\"year\": \"2015\", \"aging_rate\": 16.7}, {\"year\": \"2020\", \"aging_rate\": 16.3}], \"latest_aging_rate\": 16.3, \"national_aging_history\": [{\"year\": \"2000\", \"aging_rate\": 17.3}, {\"year\": \"2005\", \"aging_rate\": 20.2}, {\"year\": \"2010\", \"aging_rate\": 23.0}, {\"year\": \"2015\", \"aging_rate\": 26.6}, {\"year\": \"2020\", \"aging_rate\": 28.6}], \"tokyo23_avg_aging_history\": [{\"year\": \"2000\", \"aging_rate\": 17.5}, {\"year\": \"2005\", \"aging_rate\": 18.9}, {\"year\": \"2010\", \"aging_rate\": 20.2}, {\"year\": \"2015\", \"aging_rate\": 21.4}, {\"year\": \"2020\", \"aging_rate\": 21.1}]}", "is_new": false, "is_new_building": false, "price_history": [{"date": "2026-03-25", "price_man": 11900}], "first_seen_at": "2026-03-22", "competing_listings_count": 2, "price_fairness_score": null, "resale_liquidity_score": 67, "listing_score": 78}, {"source": "suumo", "property_type": "shinchiku", "url": "https://suumo.jp/ms/shinchiku/tokyo/sc_chuo/nc_20144751/", "name": "HARUMI FLAG PARK VILLAGE　T棟", "price_man": 11950, "price_max_man": 11950, "address": "東京都中央区晴海５-6-7", "station_line": "都営大江戸線/勝どき 徒歩15分", "walk_min": 15, "area_m2": null, "area_max_m2": null, "layout": "2LDK", "delivery_date": "相談", "total_units": null, "floor_total": 13, "list_ward_roman": "chuo", "built_str": "", "built_year": null, "floor_position": null, "floor_structure": null, "ownership": null, "duplicate_count": 1, "latitude": 35.6498252, "longitude": 139.7731905, "ss_appreciation_rate": 107.7, "ss_sumai_surfin_url": "https://www.sumai-surfin.com/re/42281/", "ss_oki_price_70m2": 13440, "ss_address": "東京都中央区晴海５－６", "ss_favorite_count": 162, "ss_lookup_status": "found", "ss_sim_base_price": 14990, "ss_surrounding_properties": "[{\"name\": \"ＴＨＥ　ＴＯＫＹＯ　ＴＯＷＥＲＳ（ザ・トーキョー・タワーズ）\", \"url\": \"https://www.sumai-surfin.com/re/1973/\", \"appreciation_rate\": 160.6, \"oki_price_70m2\": 11550}, {\"name\": \"セザールアクアフロント勝どきイースト\", \"url\": \"https://www.sumai-surfin.com/re/16055/\", \"appreciation_rate\": 143.3, \"oki_price_70m2\": 9590}, {\"name\": \"セザールリバーサイド月島\", \"url\": \"https://www.sumai-surfin.com/re/16063/\", \"appreciation_rate\": 139.6, \"oki_price_70m2\": 9590}, {\"name\": \"ＨＡＲＵＭＩ　ＦＬＡＧ　ＳＥＡ　ＶＩＬＬＡＧＥ（Ａ～Ｅ棟）\", \"url\": \"https://www.sumai-surfin.com/re/42271/\", \"appreciation_rate\": 137.0, \"oki_price_70m2\": 14700}, {\"name\": \"プラネ勝どき\", \"url\": \"https://www.sumai-surfin.com/re/1039/\", \"appreciation_rate\": 125.2, \"oki_price_70m2\": 8960}, {\"name\": \"アルス勝どきコモーネ\", \"url\": \"https://www.sumai-surfin.com/re/13119/\", \"appreciation_rate\": 123.4, \"oki_price_70m2\": 9030}, {\"name\": \"セザールアクアフロント勝どきウエスト\", \"url\": \"https://www.sumai-surfin.com/re/16056/\", \"appreciation_rate\": 119.4, \"oki_price_70m2\": 8610}, {\"name\": \"アスコットパーク勝どき\", \"url\": \"https://www.sumai-surfin.com/re/2120/\", \"appreciation_rate\": 117.7, \"oki_price_70m2\": 10220}, {\"name\": \"晴海テラス\", \"url\": \"https://www.sumai-surfin.com/re/11144/\", \"appreciation_rate\": 115.6, \"oki_price_70m2\": 9590}, {\"name\": \"クレアシティ勝どきアットステーション\", \"url\": \"https://www.sumai-surfin.com/re/13817/\", \"appreciation_rate\": 114.2, \"oki_price_70m2\": 8680}]", "ss_purchase_judgment": "条件付きで値上がりが期待できます", "geocode_confidence": "high", "hazard_info": "{\"flood\": false, \"sediment\": false, \"storm_surge\": false, \"tsunami\": false, \"liquefaction\": false, \"inland_water\": false, \"building_collapse\": 1, \"fire\": 1, \"combined\": 1}", "commute_info": "{\"playground\": {\"minutes\": 18, \"summary\": \"Google Maps経路 (朝9:00到着)\", \"calculatedAt\": \"2026-03-25T06:29:41Z\", \"source\": \"gmaps\"}, \"m3career\": {\"minutes\": 12, \"summary\": \"Google Maps経路 (朝9:00到着)\", \"calculatedAt\": \"2026-03-25T06:29:41Z\", \"source\": \"gmaps\"}}", "reinfolib_market_data": "{\"ward\": \"中央区\", \"ward_median_m2_price\": 1669697, \"ward_mean_m2_price\": 1673121, \"price_ratio\": null, \"price_diff_man\": null, \"sample_count\": 78, \"match_tier\": 1, \"match_description\": \"中央区・2LDK\", \"trend\": \"flat\", \"yoy_change_pct\": 33.1, \"quarterly_m2_prices\": [{\"quarter\": \"2024Q1\", \"median_m2_price\": 1414973, \"count\": 100}, {\"quarter\": \"2024Q2\", \"median_m2_price\": 1288889, \"count\": 99}, {\"quarter\": \"2024Q3\", \"median_m2_price\": 1381818, \"count\": 99}, {\"quarter\": \"2024Q4\", \"median_m2_price\": 1633333, \"count\": 100}, {\"quarter\": \"2025Q1\", \"median_m2_price\": 1761616, \"count\": 100}, {\"quarter\": \"2025Q2\", \"median_m2_price\": 1857143, \"count\": 100}, {\"quarter\": \"2025Q3\", \"median_m2_price\": 1839744, \"count\": 100}], \"yearly_m2_prices\": [{\"year\": \"2021\", \"median_m2_price\": 1200000, \"count\": 19}, {\"year\": \"2022\", \"median_m2_price\": 1225000, \"count\": 20}, {\"year\": \"2023\", \"median_m2_price\": 1300000, \"count\": 20}, {\"year\": \"2024\", \"median_m2_price\": 1400000, \"count\": 21}, {\"year\": \"2025\", \"median_m2_price\": 1592857, \"count\": 19}], \"same_building_transactions\": [], \"station\": null, \"data_source\": \"不動産情報ライブラリ（国土交通省）\"}", "estat_population_data": "{\"ward\": \"中央区\", \"latest_population\": 187462, \"latest_households\": 101935, \"pop_change_1yr_pct\": 3.2, \"pop_change_5yr_pct\": 17.5, \"population_history\": [{\"year\": \"2020\", \"population\": 169179}, {\"year\": \"2021\", \"population\": 170504}, {\"year\": \"2022\", \"population\": 174924}, {\"year\": \"2023\", \"population\": 181653}, {\"year\": \"2024\", \"population\": 187462}], \"household_history\": [{\"year\": \"2020\", \"households\": 90240}, {\"year\": \"2021\", \"households\": 91830}, {\"year\": \"2022\", \"households\": 94750}, {\"year\": \"2023\", \"households\": 98930}, {\"year\": \"2024\", \"households\": 101935}], \"data_source\": \"e-Stat 政府統計（総務省）住民基本台帳に基づく人口\", \"aging_rate_history\": [{\"year\": \"2000\", \"aging_rate\": 19.5}, {\"year\": \"2005\", \"aging_rate\": 17.5}, {\"year\": \"2010\", \"aging_rate\": 16.2}, {\"year\": \"2015\", \"aging_rate\": 16.7}, {\"year\": \"2020\", \"aging_rate\": 16.3}], \"latest_aging_rate\": 16.3, \"national_aging_history\": [{\"year\": \"2000\", \"aging_rate\": 17.3}, {\"year\": \"2005\", \"aging_rate\": 20.2}, {\"year\": \"2010\", \"aging_rate\": 23.0}, {\"year\": \"2015\", \"aging_rate\": 26.6}, {\"year\": \"2020\", \"aging_rate\": 28.6}], \"tokyo23_avg_aging_history\": [{\"year\": \"2000\", \"aging_rate\": 17.5}, {\"year\": \"2005\", \"aging_rate\": 18.9}, {\"year\": \"2010\", \"aging_rate\": 20.2}, {\"year\": \"2015\", \"aging_rate\": 21.4}, {\"year\": \"2020\", \"aging_rate\": 21.1}]}", "is_new": false, "is_new_building": false, "price_history": [{"date": "2026-03-25", "price_man": 11900}, {"date": "2026-03-28", "price_man": 11950}], "first_seen_at": "2026-03-22", "competing_listings_count": 2, "price_fairness_score": null, "resale_liquidity_score": 67, "listing_score": 78}, {"source": "suumo", "property_type": "shinchiku", "url": "https://suumo.jp/ms/shinchiku/tokyo/sc_minato/nc_78656991/", "name": "ジオグランデ白金台", "price_man": null, "price_max_man": 7000, "address": "東京都港区白金台３", "station_line": "東京メトロ南北線/白金台 徒歩4分", "walk_min": 4, "area_m2": null, "area_max_m2": null, "layout": "2LDK+S（納戸）", "delivery_date": "即引渡可", "total_units": null, "floor_total": 15, "list_ward_roman": "minato", "built_str": "", "built_year": null, "floor_position": null, "floor_structure": null, "ownership": null, "duplicate_count": 1, "ss_sumai_surfin_url": "https://www.sumai-surfin.com/re/47980/", "ss_address": "東京都港区白金台３－５１－１", "ss_favorite_count": 58, "ss_lookup_status": "found", "ss_sim_base_price": 6000, "ss_purchase_judgment": "条件付きで値上がりが期待できます", "commute_info": "{\"playground\": {\"minutes\": 16, \"summary\": \"Google Maps経路 (朝9:00到着)\", \"calculatedAt\": \"2026-03-25T06:29:41Z\", \"source\": \"gmaps\"}, \"m3career\": {\"minutes\": 12, \"summary\": \"Google Maps経路 (朝9:00到着)\", \"calculatedAt\": \"2026-03-25T06:29:41Z\", \"source\": \"gmaps\"}}", "reinfolib_market_data": "{\"ward\": \"港区\", \"ward_median_m2_price\": 2166667, \"ward_mean_m2_price\": 2471684, \"price_ratio\": null, \"price_diff_man\": null, \"sample_count\": 69, \"match_tier\": 1, \"match_description\": \"港区・2LDK\", \"trend\": \"up\", \"yoy_change_pct\": 42.6, \"quarterly_m2_prices\": [{\"quarter\": \"2024Q1\", \"median_m2_price\": 1714286, \"count\": 100}, {\"quarter\": \"2024Q2\", \"median_m2_price\": 1651515, \"count\": 100}, {\"quarter\": \"2024Q3\", \"median_m2_price\": 1636667, \"count\": 100}, {\"quarter\": \"2024Q4\", \"median_m2_price\": 1955000, \"count\": 100}, {\"quarter\": \"2025Q1\", \"median_m2_price\": 2000000, \"count\": 99}, {\"quarter\": \"2025Q2\", \"median_m2_price\": 2194444, \"count\": 98}, {\"quarter\": \"2025Q3\", \"median_m2_price\": 2333333, \"count\": 97}], \"yearly_m2_prices\": [{\"year\": \"2021\", \"median_m2_price\": 1390178, \"count\": 28}, {\"year\": \"2022\", \"median_m2_price\": 1450000, \"count\": 29}, {\"year\": \"2023\", \"median_m2_price\": 1535000, \"count\": 30}, {\"year\": \"2024\", \"median_m2_price\": 1837321, \"count\": 30}, {\"year\": \"2025\", \"median_m2_price\": 1892857, \"count\": 28}], \"same_building_transactions\": [], \"station\": null, \"data_source\": \"不動産情報ライブラリ（国土交通省）\"}", "estat_population_data": "{\"ward\": \"港区\", \"latest_population\": 262085, \"latest_households\": 148715, \"pop_change_1yr_pct\": 1.5, \"pop_change_5yr_pct\": 6.8, \"population_history\": [{\"year\": \"2020\", \"population\": 260486}, {\"year\": \"2021\", \"population\": 257978}, {\"year\": \"2022\", \"population\": 256274}, {\"year\": \"2023\", \"population\": 258204}, {\"year\": \"2024\", \"population\": 262085}], \"household_history\": [{\"year\": \"2020\", \"households\": 144298}, {\"year\": \"2021\", \"households\": 143682}, {\"year\": \"2022\", \"households\": 144120}, {\"year\": \"2023\", \"households\": 146530}, {\"year\": \"2024\", \"households\": 148715}], \"data_source\": \"e-Stat 政府統計（総務省）住民基本台帳に基づく人口\", \"aging_rate_history\": [{\"year\": \"2000\", \"aging_rate\": 18.0}, {\"year\": \"2005\", \"aging_rate\": 17.7}, {\"year\": \"2010\", \"aging_rate\": 17.3}, {\"year\": \"2015\", \"aging_rate\": 17.9}, {\"year\": \"2020\", \"aging_rate\": 17.1}], \"latest_aging_rate\": 17.1, \"national_aging_history\": [{\"year\": \"2000\", \"aging_rate\": 17.3}, {\"year\": \"2005\", \"aging_rate\": 20.2}, {\"year\": \"2010\", \"aging_rate\": 23.0}, {\"year\": \"2015\", \"aging_rate\": 26.6}, {\"year\": \"2020\", \"aging_rate\": 28.6}], \"tokyo23_avg_aging_history\": [{\"year\": \"2000\", \"aging_rate\": 17.5}, {\"year\": \"2005\", \"aging_rate\": 18.9}, {\"year\": \"2010\", \"aging_rate\": 20.2}, {\"year\": \"2015\", \"aging_rate\": 21.4}, {\"year\": \"2020\", \"aging_rate\": 21.1}]}", "is_new": false, "is_new_building": false, "price_history": [], "first_seen_at": "2026-03-22", "competing_listings_count": 2, "price_fairness_score": null, "resale_liquidity_score": 82, "listing_score": 86}, {"source": "suumo", "property_type": "shinchiku", "url": "https://suumo.jp/ms/shinchiku/tokyo/sc_minato/nc_79039612/", "name": "三田ガーデンヒルズ　13階　角部屋", "price_man": null, "price_max_man": null, "address": "東京都港区三田１", "station_line": "東京メトロ南北線/麻布十番 徒歩7分", "walk_min": 7, "area_m2": null, "area_max_m2": null, "layout": "2LDK", "delivery_date": "即引渡可", "total_units": null, "floor_total": 13, "list_ward_roman": "minato", "built_str": "", "built_year": null, "floor_position": null, "floor_structure": null, "ownership": null, "duplicate_count": 1, "latitude": 35.6540335, "longitude": 139.7441783, "ss_sumai_surfin_url": "https://www.sumai-surfin.com/re/46087/", "ss_address": "東京都港区三田１－１０２－１", "ss_favorite_count": 145, "ss_lookup_status": "found", "ss_sim_base_price": 39000, "ss_surrounding_properties": "[{\"name\": \"元麻布ヒルズフォレストタワー\", \"url\": \"https://www.sumai-surfin.com/re/14497/\", \"appreciation_rate\": 210.9, \"oki_price_70m2\": 28490}, {\"name\": \"フォレセーヌ麻布永坂\", \"url\": \"https://www.sumai-surfin.com/re/3890/\", \"appreciation_rate\": 183.4, \"oki_price_70m2\": 28980}, {\"name\": \"ザ・パークハウス元麻布\", \"url\": \"https://www.sumai-surfin.com/re/27704/\", \"appreciation_rate\": 171.6, \"oki_price_70m2\": 21140}, {\"name\": \"ブランズ麻布狸穴町\", \"url\": \"https://www.sumai-surfin.com/re/29318/\", \"appreciation_rate\": 169.7, \"oki_price_70m2\": 22050}, {\"name\": \"コスモ麻布十番\", \"url\": \"https://www.sumai-surfin.com/re/15768/\", \"appreciation_rate\": 165.8, \"oki_price_70m2\": 13650}, {\"name\": \"シティハイツ麻布十番\", \"url\": \"https://www.sumai-surfin.com/re/15989/\", \"appreciation_rate\": 160.2, \"oki_price_70m2\": 13510}, {\"name\": \"シティタワー麻布十番\", \"url\": \"https://www.sumai-surfin.com/re/8520/\", \"appreciation_rate\": 151.9, \"oki_price_70m2\": 24220}, {\"name\": \"パークコート麻布十番ザタワー\", \"url\": \"https://www.sumai-surfin.com/re/9212/\", \"appreciation_rate\": 148.9, \"oki_price_70m2\": 23870}, {\"name\": \"パークマンション三田綱町ザフォレスト\", \"url\": \"https://www.sumai-surfin.com/re/31812/\", \"appreciation_rate\": 146.3, \"oki_price_70m2\": 34230}, {\"name\": \"クレッセント麻布II\", \"url\": \"https://www.sumai-surfin.com/re/15554/\", \"appreciation_rate\": 140.0, \"oki_price_70m2\": 13370}]", "ss_purchase_judgment": "条件付きで値上がりが期待できます", "geocode_confidence": "high", "hazard_info": "{\"flood\": false, \"sediment\": false, \"storm_surge\": false, \"tsunami\": false, \"liquefaction\": false, \"inland_water\": false, \"building_collapse\": 1, \"fire\": 1, \"combined\": 1}", "commute_info": "{\"playground\": {\"minutes\": 16, \"summary\": \"Google Maps経路 (朝9:00到着)\", \"calculatedAt\": \"2026-03-25T06:29:41Z\", \"source\": \"gmaps\"}, \"m3career\": {\"minutes\": 9, \"summary\": \"Google Maps経路 (朝9:00到着)\", \"calculatedAt\": \"2026-03-25T06:29:41Z\", \"source\": \"gmaps\"}}", "reinfolib_market_data": "{\"ward\": \"港区\", \"ward_median_m2_price\": 2166667, \"ward_mean_m2_price\": 2471684, \"price_ratio\": null, \"price_diff_man\": null, \"sample_count\": 69, \"match_tier\": 1, \"match_description\": \"港区・2LDK\", \"trend\": \"up\", \"yoy_change_pct\": 42.6, \"quarterly_m2_prices\": [{\"quarter\": \"2024Q1\", \"median_m2_price\": 1714286, \"count\": 100}, {\"quarter\": \"2024Q2\", \"median_m2_price\": 1651515, \"count\": 100}, {\"quarter\": \"2024Q3\", \"median_m2_price\": 1636667, \"count\": 100}, {\"quarter\": \"2024Q4\", \"median_m2_price\": 1955000, \"count\": 100}, {\"quarter\": \"2025Q1\", \"median_m2_price\": 2000000, \"count\": 99}, {\"quarter\": \"2025Q2\", \"median_m2_price\": 2194444, \"count\": 98}, {\"quarter\": \"2025Q3\", \"median_m2_price\": 2333333, \"count\": 97}], \"yearly_m2_prices\": [{\"year\": \"2021\", \"median_m2_price\": 1390178, \"count\": 28}, {\"year\": \"2022\", \"median_m2_price\": 1450000, \"count\": 29}, {\"year\": \"2023\", \"median_m2_price\": 1535000, \"count\": 30}, {\"year\": \"2024\", \"median_m2_price\": 1837321, \"count\": 30}, {\"year\": \"2025\", \"median_m2_price\": 1892857, \"count\": 28}], \"same_building_transactions\": [], \"station\": null, \"data_source\": \"不動産情報ライブラリ（国土交通省）\"}", "estat_population_data": "{\"ward\": \"港区\", \"latest_population\": 262085, \"latest_households\": 148715, \"pop_change_1yr_pct\": 1.5, \"pop_change_5yr_pct\": 6.8, \"population_history\": [{\"year\": \"2020\", \"population\": 260486}, {\"year\": \"2021\", \"population\": 257978}, {\"year\": \"2022\", \"population\": 256274}, {\"year\": \"2023\", \"population\": 258204}, {\"year\": \"2024\", \"population\": 262085}], \"household_history\": [{\"year\": \"2020\", \"households\": 144298}, {\"year\": \"2021\", \"households\": 143682}, {\"year\": \"2022\", \"households\": 144120}, {\"year\": \"2023\", \"households\": 146530}, {\"year\": \"2024\", \"households\": 148715}], \"data_source\": \"e-Stat 政府統計（総務省）住民基本台帳に基づく人口\", \"aging_rate_history\": [{\"year\": \"2000\", \"aging_rate\": 18.0}, {\"year\": \"2005\", \"aging_rate\": 17.7}, {\"year\": \"2010\", \"aging_rate\": 17.3}, {\"year\": \"2015\", \"aging_rate\": 17.9}, {\"year\": \"2020\", \"aging_rate\": 17.1}], \"latest_aging_rate\": 17.1, \"national_aging_history\": [{\"year\": \"2000\", \"aging_rate\": 17.3}, {\"year\": \"2005\", \"aging_rate\": 20.2}, {\"year\": \"2010\", \"aging_rate\": 23.0}, {\"year\": \"2015\", \"aging_rate\": 26.6}, {\"year\": \"2020\", \"aging_rate\": 28.6}], \"tokyo23_avg_aging_history\": [{\"year\": \"2000\", \"aging_rate\": 17.5}, {\"year\": \"2005\", \"aging_rate\": 18.9}, {\"year\": \"2010\", \"aging_rate\": 20.2}, {\"year\": \"2015\", \"aging_rate\": 21.4}, {\"year\": \"2020\", \"aging_rate\": 21.1}]}", "is_new": false, "is_new_building": false, "price_history": [], "first_seen_at": "2026-03-22", "competing_listings_count": 1, "price_fairness_score": null, "resale_liquidity_score": 76, "listing_score": 74}, {"source": "suumo", "property_type": "shinchiku", "url": "https://suumo.jp/ms/shinchiku/tokyo/sc_minato/nc_77624246/", "name": "麻布台ヒルズレジデンスＢ", "price_man": null, "price_max_man": null, "address": "東京都港区麻布台１", "station_line": "東京メトロ南北線/六本木一丁目 徒歩1分", "walk_min": 1, "area_m2": 70.28, "area_max_m2": 70.28, "layout": "2SLDK", "delivery_date": "2026年8月予定", "total_units": null, "floor_total": null, "list_ward_roman": "minato", "built_str": "", "built_year": null, "floor_position": null, "floor_structure": null, "ownership": null, "duplicate_count": 1, "latitude": 35.6608421, "longitude": 139.7406517, "ss_lookup_status": "not_found", "geocode_confidence": "high", "hazard_info": "{\"flood\": false, \"sediment\": false, \"storm_surge\": false, \"tsunami\": false, \"liquefaction\": false, \"inland_water\": false, \"building_collapse\": 2, \"fire\": 1, \"combined\": 2}", "commute_info": "{\"playground\": {\"minutes\": 12, \"summary\": \"Google Maps経路 (朝9:00到着)\", \"calculatedAt\": \"2026-03-25T06:29:41Z\", \"source\": \"gmaps\"}, \"m3career\": {\"minutes\": 2, \"summary\": \"Google Maps経路 (朝9:00到着)\", \"calculatedAt\": \"2026-03-25T06:29:41Z\", \"source\": \"gmaps\"}}", "reinfolib_market_data": "{\"ward\": \"港区\", \"ward_median_m2_price\": 2125000, \"ward_mean_m2_price\": 2492168, \"price_ratio\": null, \"price_diff_man\": null, \"sample_count\": 51, \"match_tier\": 1, \"match_description\": \"港区・2LDK・55-85m²\", \"trend\": \"up\", \"yoy_change_pct\": 42.6, \"quarterly_m2_prices\": [{\"quarter\": \"2024Q1\", \"median_m2_price\": 1714286, \"count\": 100}, {\"quarter\": \"2024Q2\", \"median_m2_price\": 1651515, \"count\": 100}, {\"quarter\": \"2024Q3\", \"median_m2_price\": 1636667, \"count\": 100}, {\"quarter\": \"2024Q4\", \"median_m2_price\": 1955000, \"count\": 100}, {\"quarter\": \"2025Q1\", \"median_m2_price\": 2000000, \"count\": 99}, {\"quarter\": \"2025Q2\", \"median_m2_price\": 2194444, \"count\": 98}, {\"quarter\": \"2025Q3\", \"median_m2_price\": 2333333, \"count\": 97}], \"yearly_m2_prices\": [{\"year\": \"2021\", \"median_m2_price\": 1390178, \"count\": 28}, {\"year\": \"2022\", \"median_m2_price\": 1450000, \"count\": 29}, {\"year\": \"2023\", \"median_m2_price\": 1535000, \"count\": 30}, {\"year\": \"2024\", \"median_m2_price\": 1837321, \"count\": 30}, {\"year\": \"2025\", \"median_m2_price\": 1892857, \"count\": 28}], \"same_building_transactions\": [], \"station\": null, \"data_source\": \"不動産情報ライブラリ（国土交通省）\"}", "estat_population_data": "{\"ward\": \"港区\", \"latest_population\": 262085, \"latest_households\": 148715, \"pop_change_1yr_pct\": 1.5, \"pop_change_5yr_pct\": 6.8, \"population_history\": [{\"year\": \"2020\", \"population\": 260486}, {\"year\": \"2021\", \"population\": 257978}, {\"year\": \"2022\", \"population\": 256274}, {\"year\": \"2023\", \"population\": 258204}, {\"year\": \"2024\", \"population\": 262085}], \"household_history\": [{\"year\": \"2020\", \"households\": 144298}, {\"year\": \"2021\", \"households\": 143682}, {\"year\": \"2022\", \"households\": 144120}, {\"year\": \"2023\", \"households\": 146530}, {\"year\": \"2024\", \"households\": 148715}], \"data_source\": \"e-Stat 政府統計（総務省）住民基本台帳に基づく人口\", \"aging_rate_history\": [{\"year\": \"2000\", \"aging_rate\": 18.0}, {\"year\": \"2005\", \"aging_rate\": 17.7}, {\"year\": \"2010\", \"aging_rate\": 17.3}, {\"year\": \"2015\", \"aging_rate\": 17.9}, {\"year\": \"2020\", \"aging_rate\": 17.1}], \"latest_aging_rate\": 17.1, \"national_aging_history\": [{\"year\": \"2000\", \"aging_rate\": 17.3}, {\"year\": \"2005\", \"aging_rate\": 20.2}, {\"year\": \"2010\", \"aging_rate\": 23.0}, {\"year\": \"2015\", \"aging_rate\": 26.6}, {\"year\": \"2020\", \"aging_rate\": 28.6}], \"tokyo23_avg_aging_history\": [{\"year\": \"2000\", \"aging_rate\": 17.5}, {\"year\": \"2005\", \"aging_rate\": 18.9}, {\"year\": \"2010\", \"aging_rate\": 20.2}, {\"year\": \"2015\", \"aging_rate\": 21.4}, {\"year\": \"2020\", \"aging_rate\": 21.1}]}", "is_new": false, "is_new_building": false, "price_history": [], "first_seen_at": "2026-03-22", "competing_listings_count": 1, "price_fairness_score": null, "resale_liquidity_score": 88, "listing_score": 79}, {"source": "suumo", "property_type": "shinchiku", "url": "https://suumo.jp/ms/shinchiku/tokyo/sc_minato/nc_20484278/", "name": "ジオグランデ白金台", "price_man": null, "price_max_man": null, "address": "東京都港区白金台３-16-4", "station_line": "東京メトロ南北線/白金台 徒歩6分", "walk_min": 6, "area_m2": 115.57, "area_max_m2": 115.57, "layout": "3LDK", "delivery_date": "即引渡可", "total_units": null, "floor_total": null, "list_ward_roman": "minato", "built_str": "", "built_year": null, "floor_position": null, "floor_structure": null, "ownership": null, "duplicate_count": 1, "ss_sumai_surfin_url": "https://www.sumai-surfin.com/re/47980/", "ss_address": "東京都港区白金台３－５１－１", "ss_favorite_count": 58, "ss_lookup_status": "found", "ss_sim_base_price": 6000, "ss_purchase_judgment": "条件付きで値上がりが期待できます", "commute_info": "{\"playground\": {\"minutes\": 16, \"summary\": \"Google Maps経路 (朝9:00到着)\", \"calculatedAt\": \"2026-03-25T06:29:41Z\", \"source\": \"gmaps\"}, \"m3career\": {\"minutes\": 12, \"summary\": \"Google Maps経路 (朝9:00到着)\", \"calculatedAt\": \"2026-03-25T06:29:41Z\", \"source\": \"gmaps\"}}", "reinfolib_market_data": "{\"ward\": \"港区\", \"ward_median_m2_price\": 2500000, \"ward_mean_m2_price\": 2815580, \"price_ratio\": null, \"price_diff_man\": null, \"sample_count\": 17, \"match_tier\": 3, \"match_description\": \"港区・3LDK\", \"trend\": \"up\", \"yoy_change_pct\": 42.6, \"quarterly_m2_prices\": [{\"quarter\": \"2024Q1\", \"median_m2_price\": 1714286, \"count\": 100}, {\"quarter\": \"2024Q2\", \"median_m2_price\": 1651515, \"count\": 100}, {\"quarter\": \"2024Q3\", \"median_m2_price\": 1636667, \"count\": 100}, {\"quarter\": \"2024Q4\", \"median_m2_price\": 1955000, \"count\": 100}, {\"quarter\": \"2025Q1\", \"median_m2_price\": 2000000, \"count\": 99}, {\"quarter\": \"2025Q2\", \"median_m2_price\": 2194444, \"count\": 98}, {\"quarter\": \"2025Q3\", \"median_m2_price\": 2333333, \"count\": 97}], \"yearly_m2_prices\": [{\"year\": \"2021\", \"median_m2_price\": 1390178, \"count\": 28}, {\"year\": \"2022\", \"median_m2_price\": 1450000, \"count\": 29}, {\"year\": \"2023\", \"median_m2_price\": 1535000, \"count\": 30}, {\"year\": \"2024\", \"median_m2_price\": 1837321, \"count\": 30}, {\"year\": \"2025\", \"median_m2_price\": 1892857, \"count\": 28}], \"same_building_transactions\": [], \"station\": null, \"data_source\": \"不動産情報ライブラリ（国土交通省）\"}", "estat_population_data": "{\"ward\": \"港区\", \"latest_population\": 262085, \"latest_households\": 148715, \"pop_change_1yr_pct\": 1.5, \"pop_change_5yr_pct\": 6.8, \"population_history\": [{\"year\": \"2020\", \"population\": 260486}, {\"year\": \"2021\", \"population\": 257978}, {\"year\": \"2022\", \"population\": 256274}, {\"year\": \"2023\", \"population\": 258204}, {\"year\": \"2024\", \"population\": 262085}], \"household_history\": [{\"year\": \"2020\", \"households\": 144298}, {\"year\": \"2021\", \"households\": 143682}, {\"year\": \"2022\", \"households\": 144120}, {\"year\": \"2023\", \"households\": 146530}, {\"year\": \"2024\", \"households\": 148715}], \"data_source\": \"e-Stat 政府統計（総務省）住民基本台帳に基づく人口\", \"aging_rate_history\": [{\"year\": \"2000\", \"aging_rate\": 18.0}, {\"year\": \"2005\", \"aging_rate\": 17.7}, {\"year\": \"2010\", \"aging_rate\": 17.3}, {\"year\": \"2015\", \"aging_rate\": 17.9}, {\"year\": \"2020\", \"aging_rate\": 17.1}], \"latest_aging_rate\": 17.1, \"national_aging_history\": [{\"year\": \"2000\", \"aging_rate\": 17.3}, {\"year\": \"2005\", \"aging_rate\": 20.2}, {\"year\": \"2010\", \"aging_rate\": 23.0}, {\"year\": \"2015\", \"aging_rate\": 26.6}, {\"year\": \"2020\", \"aging_rate\": 28.6}], \"tokyo23_avg_aging_history\": [{\"year\": \"2000\", \"aging_rate\": 17.5}, {\"year\": \"2005\", \"aging_rate\": 18.9}, {\"year\": \"2010\", \"aging_rate\": 20.2}, {\"year\": \"2015\", \"aging_rate\": 21.4}, {\"year\": \"2020\", \"aging_rate\": 21.1}]}", "is_new": false, "is_new_building": false, "price_history": [], "first_seen_at": "2026-03-22", "competing_listings_count": 2, "price_fairness_score": null, "resale_liquidity_score": 72, "listing_score": 81}, {"source": "suumo", "property_type": "shinchiku", "url": "https://suumo.jp/ms/shinchiku/tokyo/sc_shinjuku/nc_67726630/", "name": "クラッシィタワー新宿御苑", "price_man": null, "price_max_man": null, "address": "新宿区四谷４", "station_line": "東京メトロ丸ノ内線/新宿御苑前 徒歩4分", "walk_min": 4, "area_m2": null, "area_max_m2": null, "layout": "2LDK", "delivery_date": "2026年3月下旬", "total_units": null, "floor_total": null, "list_ward_roman": "shinjuku", "built_str": "", "built_year": null, "floor_position": null, "floor_structure": null, "ownership": null, "duplicate_count": 1, "ss_appreciation_rate": 68.6, "ss_sumai_surfin_url": "https://www.sumai-surfin.com/re/46646/", "ss_address": "東京都新宿区四谷４－２９－３", "ss_favorite_count": 233, "ss_lookup_status": "found", "ss_sim_base_price": 33980, "ss_surrounding_properties": "[{\"name\": \"Ｔｏｍｉｈｉｓａ　Ｃｒｏｓｓ　（富久クロス）\", \"url\": \"https://www.sumai-surfin.com/re/30218/\", \"appreciation_rate\": 148.2, \"oki_price_70m2\": 16660}, {\"name\": \"ザ・ミッドハウス新宿御苑\", \"url\": \"https://www.sumai-surfin.com/re/28838/\", \"appreciation_rate\": 116.5, \"oki_price_70m2\": 14070}, {\"name\": \"ザ・パークハウス新宿御苑\", \"url\": \"https://www.sumai-surfin.com/re/38681/\", \"appreciation_rate\": 106.5, \"oki_price_70m2\": 24430}, {\"name\": \"ヒルズ新宿御苑\", \"url\": \"https://www.sumai-surfin.com/re/14222/\", \"appreciation_rate\": 102.7, \"oki_price_70m2\": 15890}, {\"name\": \"ローレルコート新宿タワー\", \"url\": \"https://www.sumai-surfin.com/re/11796/\", \"appreciation_rate\": 96.8, \"oki_price_70m2\": 10500}, {\"name\": \"セレビア新宿御苑前\", \"url\": \"https://www.sumai-surfin.com/re/668/\", \"appreciation_rate\": 95.9, \"oki_price_70m2\": 10850}, {\"name\": \"パークリュクス新宿御苑前ｍｏｎｏ\", \"url\": \"https://www.sumai-surfin.com/re/30728/\", \"appreciation_rate\": 94.3, \"oki_price_70m2\": 12530}, {\"name\": \"フォルム内藤町\", \"url\": \"https://www.sumai-surfin.com/re/8180/\", \"appreciation_rate\": 84.8, \"oki_price_70m2\": 15750}, {\"name\": \"朝日新宿御苑マンション\", \"url\": \"https://www.sumai-surfin.com/re/20222/\", \"appreciation_rate\": 82.9, \"oki_price_70m2\": 13300}, {\"name\": \"新宿御苑サニーコート\", \"url\": \"https://www.sumai-surfin.com/re/19390/\", \"appreciation_rate\": 75.8, \"oki_price_70m2\": 9800}]", "ss_purchase_judgment": "条件付きで値上がりが期待できます", "commute_info": "{\"playground\": {\"minutes\": 11, \"summary\": \"Google Maps経路 (朝9:00到着)\", \"calculatedAt\": \"2026-03-25T06:29:41Z\", \"source\": \"gmaps\"}, \"m3career\": {\"minutes\": 16, \"summary\": \"Google Maps経路 (朝9:00到着)\", \"calculatedAt\": \"2026-03-25T06:29:41Z\", \"source\": \"gmaps\"}}", "is_new": false, "is_new_building": false, "price_history": [], "first_seen_at": "2026-03-22", "competing_listings_count": 1, "price_fairness_score": null, "resale_liquidity_score": 82, "listing_score": 87}, {"source": "suumo", "property_type": "shinchiku", "url": "https://suumo.jp/ms/shinchiku/tokyo/sc_minato/nc_67730932/", "name": "Brillia(ブリリア) Tower 乃木坂", "price_man": null, "price_max_man": null, "address": "港区南青山１", "station_line": "東京メトロ千代田線/乃木坂 徒歩1分", "walk_min": 1, "area_m2": null, "area_max_m2": null, "layout": "2LDK～3LDK", "delivery_date": "2029年1月下旬予定", "total_units": null, "floor_total": null, "list_ward_roman": "minato", "built_str": "", "built_year": null, "floor_position": null, "floor_structure": null, "ownership": null, "duplicate_count": 1, "ss_lookup_status": "not_found", "commute_info": "{\"playground\": {\"minutes\": 12, \"summary\": \"Google Maps経路 (朝9:00到着)\", \"calculatedAt\": \"2026-03-25T06:29:41Z\", \"source\": \"gmaps\"}, \"m3career\": {\"minutes\": 9, \"summary\": \"Google Maps経路 (朝9:00到着)\", \"calculatedAt\": \"2026-03-25T06:29:41Z\", \"source\": \"gmaps\"}}", "is_new": false, "is_new_building": false, "price_history": [], "first_seen_at": "2026-03-22", "competing_listings_count": 1, "price_fairness_score": null, "resale_liquidity_score": 89, "listing_score": 89}, {"source": "suumo", "property_type": "shinchiku", "url": "https://suumo.jp/ms/shinchiku/tokyo/sc_nakano/nc_67734524/", "name": "Brillia(ブリリア)方南町", "price_man": null, "price_max_man": null, "address": "中野区南台５", "station_line": "東京メトロ丸ノ内線/方南町 徒歩5分", "walk_min": 5, "area_m2": null, "area_max_m2": null, "layout": "1LDK～4LDK", "delivery_date": "2028年4月下旬予定", "total_units": null, "floor_total": null, "list_ward_roman": "nakano", "built_str": "", "built_year": null, "floor_position": null, "floor_structure": null, "ownership": null, "duplicate_count": 1, "ss_sumai_surfin_url": "https://www.sumai-surfin.com/re/49601/", "ss_profit_pct": 70, "ss_address": "東京都中野区南台５－６５－１", "ss_favorite_count": 48, "ss_lookup_status": "found", "ss_sim_base_price": 6000, "ss_purchase_judgment": "条件付きで値上がりが期待できます", "commute_info": "{\"playground\": {\"minutes\": 35, \"summary\": \"Google Maps経路 (朝9:00到着)\", \"calculatedAt\": \"2026-03-25T06:29:41Z\", \"source\": \"gmaps\"}, \"m3career\": {\"minutes\": 28, \"summary\": \"Google Maps経路 (朝9:00到着)\", \"calculatedAt\": \"2026-03-25T06:29:41Z\", \"source\": \"gmaps\"}}", "is_new": false, "is_new_building": false, "price_history": [], "first_seen_at": "2026-03-22", "competing_listings_count": 1, "price_fairness_score": null, "resale_liquidity_score": 77, "listing_score": 67}, {"source": "suumo", "property_type": "shinchiku", "url": "https://suumo.jp/ms/shinchiku/tokyo/sc_shinjuku/nc_67733884/", "name": "ディアナコート四谷", "price_man": null, "price_max_man": null, "address": "新宿区若葉１", "station_line": "ＪＲ中央線/四ツ谷 徒歩5分", "walk_min": 5, "area_m2": null, "area_max_m2": null, "layout": "2LDK+S（納戸）・", "delivery_date": "2027年1月下旬予定", "total_units": null, "floor_total": null, "list_ward_roman": "shinjuku", "built_str": "", "built_year": null, "floor_position": null, "floor_structure": null, "ownership": null, "duplicate_count": 1, "ss_sumai_surfin_url": "https://www.sumai-surfin.com/re/49369/", "ss_profit_pct": 80, "ss_address": "東京都新宿区若葉１－１３－１外", "ss_favorite_count": 67, "ss_lookup_status": "found", "ss_sim_base_price": 6000, "ss_purchase_judgment": "条件付きで値上がりが期待できます", "commute_info": "{\"playground\": {\"minutes\": 7, \"summary\": \"Google Maps経路 (朝9:00到着)\", \"calculatedAt\": \"2026-03-25T06:29:41Z\", \"source\": \"gmaps\"}, \"m3career\": {\"minutes\": 12, \"summary\": \"Google Maps経路 (朝9:00到着)\", \"calculatedAt\": \"2026-03-25T06:29:41Z\", \"source\": \"gmaps\"}}", "is_new": false, "is_new_building": false, "price_history": [], "first_seen_at": "2026-03-22", "competing_listings_count": 1, "price_fairness_score": null, "resale_liquidity_score": 82, "listing_score": 84}]